Workbook

Sheet 28.9 Dataset_limpio_A1
A1: ID_Cliente | B1: RUT_Cliente | C1: Nombre_Completo | D1: Email_Contacto | E1: Comuna | F1: Ciudad | G1: Region | H1: Monto_Facturado_CLP | I1: Dias_Morosidad | J1: Estado_Cuenta | K1: Fecha_Registro | L1: Nombre Limpio | M1: Rut Estandarizados | N1: Dirección Completa
A2: CLI-0001 | B2: 12.857.780-8 | C2: MACARENA TAPIA MORALES | D2: mac.tapia@gmail.com | E2: La Serena | F2: La Serena | G2: Región de Coquimbo | H2: 3640000 | I2: 0 | J2: En Revisión | K2: 46156 | L2: =PROPER(TRIM(C2)) -> Macarena Tapia Morales | M2: =TRIM(B2) -> 12.857.780-8 | N2: =TEXTJOIN(" - ", TRUE, E2, F2, G2) -> La Serena - La Serena - Región de Coquimbo
A3: CLI-0002 | B3: 21773005-0 | C3: Cristián Valenzuela Araya | D3: cri.valenzuela@consultora.cl | E3: Viña del Mar | F3: Valparaíso | G3: Región de Valparaíso | H3: 21080000 | I3: 60 | J3: Activo | K3: 46034 | L3: =PROPER(TRIM(C3)) -> Cristián Valenzuela Araya | M3: =TRIM(B3) -> 21773005-0 | N3: =TEXTJOIN(" - ", TRUE, E3, F3, G3) -> Viña del Mar - Valparaíso - Región de Valparaíso
A4: CLI-0003 | B4: 14.402.092-1 | C4: Andrea Silva Morales | D4: and.silva@servicios.cl | E4: Puerto Montt | F4: Puerto Montt | G4: Región de Los Lagos | H4: 7980000 | I4: 0 | J4: Activo | K4: 46194 | L4: =PROPER(TRIM(C4)) -> Andrea Silva Morales | M4: =TRIM(B4) -> 14.402.092-1 | N4: =TEXTJOIN(" - ", TRUE, E4, F4, G4) -> Puerto Montt - Puerto Montt - Región de Los Lagos
A5: CLI-0004 | B5: 21.059.002-8 | C5: IGNACIO ROJAS ESPINOZA | D5: ign.rojas@outlook.cl | E5: Concepción | F5: Concepción | G5: Región del Biobío | H5: 8180000 | I5: 30 | J5: Activo | K5: 46178 | L5: =PROPER(TRIM(C5)) -> Ignacio Rojas Espinoza | M5: =TRIM(B5) -> 21.059.002-8 | N5: =TEXTJOIN(" - ", TRUE, E5, F5, G5) -> Concepción - Concepción - Región del Biobío
A6: CLI-0005 | B6: 22320514-8 | C6: FRANCISCA SOTO SOTO | D6: fra.soto@empresa.cl | E6: Temuco | F6: Temuco | G6: Región de la Araucanía | H6: 11450000 | I6: 45 | J6: activo | K6: 46098 | L6: =PROPER(TRIM(C6)) -> Francisca Soto Soto | M6: =TRIM(B6) -> 22320514-8 | N6: =TEXTJOIN(" - ", TRUE, E6, F6, G6) -> Temuco - Temuco - Región de la Araucanía
A7: CLI-0006 | B7: 11.045.450-1 | C7: Ignacio Soto Vergara | D7: ign.soto@gmail.com | E7: Puerto Montt | F7: Puerto Montt | G7: Región de Los Lagos | H7: 13930000 | I7: 30 | J7: Activo | K7: 46170 | L7: =PROPER(TRIM(C7)) -> Ignacio Soto Vergara | M7: =TRIM(B7) -> 11.045.450-1 | N7: =TEXTJOIN(" - ", TRUE, E7, F7, G7) -> Puerto Montt - Puerto Montt - Región de Los Lagos
A8: CLI-0007 | B8: 17.684.442-7 | C8: Beatriz Tapia Silva | D8: bea.tapia@sura.cl | E8: Talcahuano | F8: Concepción | G8: Región del Biobío | H8: 13200000 | I8: 120 | J8: activo | K8: 46119 | L8: =PROPER(TRIM(C8)) -> Beatriz Tapia Silva | M8: =TRIM(B8) -> 17.684.442-7 | N8: =TEXTJOIN(" - ", TRUE, E8, F8, G8) -> Talcahuano - Concepción - Región del Biobío
A9: CLI-0008 | B9: 20.205.046-2 | C9: Mauricio Araya Tapia | D9: mau.araya@outlook.cl | E9: Santiago Centro | F9: Santiago | G9: Región Metropolitana | H9: 3170000 | I9: 0 | J9: En Revisión | K9: 46065 | L9: =PROPER(TRIM(C9)) -> Mauricio Araya Tapia | M9: =TRIM(B9) -> 20.205.046-2 | N9: =TEXTJOIN(" - ", TRUE, E9, F9, G9) -> Santiago Centro - Santiago - Región Metropolitana
A10: CLI-0009 | B10: 13660995-K | C10: carolina vergara valenzuela | D10: car.vergara@gmail.com | E10: Valparaíso | F10: Valparaíso | G10: Región de Valparaíso | H10: 18780000 | I10: 0 | J10: En Revisión | K10: 46120 | L10: =PROPER(TRIM(C10)) -> Carolina Vergara Valenzuela | M10: =TRIM(B10) -> 13660995-K | N10: =TEXTJOIN(" - ", TRUE, E10, F10, G10) -> Valparaíso - Valparaíso - Región de Valparaíso
A11: CLI-0010 | B11: 11.050.232-K | C11: TOMAS LÓPEZ RODRÍGUEZ | D11: tom.lópez@gmail.com | E11: Providencia | F11: Santiago | G11: Región Metropolitana | H11: 1840000 | I11: 0 | J11: EN REVISIÓN | K11: 46176 | L11: =PROPER(TRIM(C11)) -> Tomas López Rodríguez | M11: =TRIM(B11) -> 11.050.232-K | N11: =TEXTJOIN(" - ", TRUE, E11, F11, G11) -> Providencia - Santiago - Región Metropolitana
A12: CLI-0011 | B12: 14.532.054-2 | C12: Valentina Araya Rojas | D12: val.araya@servicios.cl | E12: Temuco | F12: Temuco | G12: Región de la Araucanía | H12: 7970000 | I12: 15 | J12: activo | K12: 46139 | L12: =PROPER(TRIM(C12)) -> Valentina Araya Rojas | M12: =TRIM(B12) -> 14.532.054-2 | N12: =TEXTJOIN(" - ", TRUE, E12, F12, G12) -> Temuco - Temuco - Región de la Araucanía
A13: CLI-0012 | B13: 19.537.899-0 | C13: ÁLVARO PÉREZ SOTO | D13: álv.pérez@consultora.cl | E13: Concepción | F13: Concepción | G13: Región del Biobío | H13: 14910000 | I13: 120 | J13: EN REVISIÓN | K13: 46209 | L13: =PROPER(TRIM(C13)) -> Álvaro Pérez Soto | M13: =TRIM(B13) -> 19.537.899-0 | N13: =TEXTJOIN(" - ", TRUE, E13, F13, G13) -> Concepción - Concepción - Región del Biobío
... A958: CLI-0957 | B958: 16.582.830-3 | C958: Loreto Valenzuela Contreras | D958: lor.valenzuela@outlook.cl | E958: La Serena | F958: La Serena | G958: Región de Coquimbo | H958: 21160000 | I958: 0 | J958: Inactivo | K958: 46030 | L958: =PROPER(TRIM(C958)) -> Loreto Valenzuela Contreras | M958: =TRIM(B958) -> 16.582.830-3 | N958: =TEXTJOIN(" - ", TRUE, E958, F958, G958) -> La Serena - La Serena - Región de Coquimbo

Sheet Dataset_limpio_A2
A1: ID_Cliente | B1: RUT_Cliente | C1: Nombre Limpio | D1: Email_Contacto | E1: Comuna | F1: Ciudad | G1: Region | H1: Monto_Facturado_CLP | I1: Dias_Morosidad | J1: Estado_Cuenta | K1: Fecha_Registro | L1: Producto | N1: Nombre Limpio | O1: Rut Estandarizados | P1: Dirección Completa | Q1: Estado de cuenta | R1: Nivel Riesgo | T1: Nombres
A2: CLI-0666 | B2: 17.907.842-1 | C2: Álvaro Araya Soto | D2: álv.araya@gmail.com | E2: Talcahuano | F2: Concepción | G2: Región del Biobío | H2: 8190000 | I2: 0 | J2: Inactivo | K2: 46197 | L2: Hipotecario | N2: =PROPER(TRIM(C2)) -> Álvaro Araya Soto | O2: =TRIM(B2) -> 17.907.842-1 | P2: =TEXTJOIN(" - ", TRUE, E2, F2, G2) -> Talcahuano - Concepción - Región del Biobío | Q2: =PROPER(J2) -> Inactivo | R2: =IFERROR(IFS(AND(I2>60, Q2="Activo"), "Riesgo Alto", OR(I2>30, Q2="En Revisión"), "Riesgo Medio", TRUE, "Riesgo Bajo"), "Sin Dato") -> Riesgo Bajo | T2: =PROPER(C2) -> Álvaro Araya Soto
A3: CLI-0734 | B3: 18.661.277-6 | C3: Álvaro Contreras Pérez | D3: álv.contreras@consultora.cl | E3: Antofagasta | F3: Antofagasta | G3: Región de Antofagasta | H3: 7870000 | I3: 45 | J3: Inactivo | K3: 46180 | L3: Línea Débito | N3: =PROPER(TRIM(C3)) -> Álvaro Contreras Pérez | O3: =TRIM(B3) -> 18.661.277-6 | P3: =TEXTJOIN(" - ", TRUE, E3, F3, G3) -> Antofagasta - Antofagasta - Región de Antofagasta | Q3: =PROPER(J3) -> Inactivo | R3: =IFERROR(IFS(AND(I3>60, Q3="Activo"), "Riesgo Alto", OR(I3>30, Q3="En Revisión"), "Riesgo Medio", TRUE, "Riesgo Bajo"), "Sin Dato") -> Riesgo Medio | T3: =PROPER(C$3) -> Álvaro Contreras Pérez
A4: CLI-0924 | B4: 19.532.688-1 | C4: Álvaro Díaz Vergara | D4: álv.díaz@consultora.cl | E4: Puerto Montt | F4: Puerto Montt | G4: Región de Los Lagos | H4: 8820000 | I4: 0 | J4: Activo | K4: 46211 | L4: Crédito Automotriz | N4: =PROPER(TRIM(C4)) -> Álvaro Díaz Vergara | O4: =TRIM(B4) -> 19.532.688-1 | P4: =TEXTJOIN(" - ", TRUE, E4, F4, G4) -> Puerto Montt - Puerto Montt - Región de Los Lagos | Q4: =PROPER(J4) -> Activo | R4: =IFERROR(IFS(AND(I4>60, Q4="Activo"), "Riesgo Alto", OR(I4>30, Q4="En Revisión"), "Riesgo Medio", TRUE, "Riesgo Bajo"), "Sin Dato") -> Riesgo Bajo | T4: =PROPER(C$4) -> Álvaro Díaz Vergara
A5: CLI-0668 | B5: 17.238.764-2 | C5: Álvaro Fuentes Araya | D5: álv.fuentes@empresa.cl | E5: Las Condes | F5: Santiago | G5: Región Metropolitana | H5: 14600000 | I5: 0 | J5: Inactivo | K5: 46223 | L5: Crédito Consumo | N5: =PROPER(TRIM(C5)) -> Álvaro Fuentes Araya | O5: =TRIM(B5) -> 17.238.764-2 | P5: =TEXTJOIN(" - ", TRUE, E5, F5, G5) -> Las Condes - Santiago - Región Metropolitana | Q5: =PROPER(J5) -> Inactivo | R5: =IFERROR(IFS(AND(I5>60, Q5="Activo"), "Riesgo Alto", OR(I5>30, Q5="En Revisión"), "Riesgo Medio", TRUE, "Riesgo Bajo"), "Sin Dato") -> Riesgo Bajo
A6: CLI-0934 | B6: 21.180.527-K | C6: Álvaro Fuentes Araya | D6: álv.fuentes@servicios.cl | E6: La Serena | F6: La Serena | G6: Región de Coquimbo | H6: 14610000 | I6: 60 | J6: Activo | K6: 46148 | L6: Crédito Estudios | N6: =PROPER(TRIM(C6)) -> Álvaro Fuentes Araya | O6: =TRIM(B6) -> 21.180.527-K | P6: =TEXTJOIN(" - ", TRUE, E6, F6, G6) -> La Serena - La Serena - Región de Coquimbo | Q6: =PROPER(J6) -> Activo | R6: =IFERROR(IFS(AND(I6>60, Q6="Activo"), "Riesgo Alto", OR(I6>30, Q6="En Revisión"), "Riesgo Medio", TRUE, "Riesgo Bajo"), "Sin Dato") -> Riesgo Medio
A7: CLI-0818 | B7: 15.617.915-5 | C7: Álvaro Fuentes González | D7: álv.fuentes@gmail.com | E7: Las Condes | F7: Santiago | G7: Región Metropolitana | H7: 5230000 | I7: 60 | J7: Activo | K7: 46156 | L7: Línea Débito | N7: =PROPER(TRIM(C7)) -> Álvaro Fuentes González | O7: =TRIM(B7) -> 15.617.915-5 | P7: =TEXTJOIN(" - ", TRUE, E7, F7, G7) -> Las Condes - Santiago - Región Metropolitana | Q7: =PROPER(J7) -> Activo | R7: =IFERROR(IFS(AND(I7>60, Q7="Activo"), "Riesgo Alto", OR(I7>30, Q7="En Revisión"), "Riesgo Medio", TRUE, "Riesgo Bajo"), "Sin Dato") -> Riesgo Medio
A8: CLI-0364 | B8: 18.809.561-9 | C8: Álvaro López Araya | D8: álv.lópez@outlook.cl | E8: Valparaíso | F8: Valparaíso | G8: Región de Valparaíso | H8: 21880000 | I8: 60 | J8: En Revisión | K8: 46094 | L8: Hipotecario | N8: =PROPER(TRIM(C8)) -> Álvaro López Araya | O8: =TRIM(B8) -> 18.809.561-9 | P8: =TEXTJOIN(" - ", TRUE, E8, F8, G8) -> Valparaíso - Valparaíso - Región de Valparaíso | Q8: =PROPER(J8) -> En Revisión | R8: =IFERROR(IFS(AND(I8>60, Q8="Activo"), "Riesgo Alto", OR(I8>30, Q8="En Revisión"), "Riesgo Medio", TRUE, "Riesgo Bajo"), "Sin Dato") -> Riesgo Medio
A9: CLI-0758 | B9: 21.871.809-9 | C9: Álvaro López Morales | D9: álv.lópez@consultora.cl | E9: Santiago Centro | F9: Santiago | G9: Región Metropolitana | H9: 6070000 | I9: 90 | J9: En Revisión | K9: 46157 | L9: Línea Débito | N9: =PROPER(TRIM(C9)) -> Álvaro López Morales | O9: =TRIM(B9) -> 21.871.809-9 | P9: =TEXTJOIN(" - ", TRUE, E9, F9, G9) -> Santiago Centro - Santiago - Región Metropolitana | Q9: =PROPER(J9) -> En Revisión | R9: =IFERROR(IFS(AND(I9>60, Q9="Activo"), "Riesgo Alto", OR(I9>30, Q9="En Revisión"), "Riesgo Medio", TRUE, "Riesgo Bajo"), "Sin Dato") -> Riesgo Medio
A10: CLI-0386 | B10: 15107618-7 | C10: Álvaro López Silva | D10: álv.lópez@empresa.cl | E10: Maipú | F10: Santiago | G10: Región Metropolitana | H10: 2150000 | I10: 60 | J10: En Revisión | K10: 46077 | L10: Crédito Automotriz | N10: =PROPER(TRIM(C10)) -> Álvaro López Silva | O10: =TRIM(B10) -> 15107618-7 | P10: =TEXTJOIN(" - ", TRUE, E10, F10, G10) -> Maipú - Santiago - Región Metropolitana | Q10: =PROPER(J10) -> En Revisión | R10: =IFERROR(IFS(AND(I10>60, Q10="Activo"), "Riesgo Alto", OR(I10>30, Q10="En Revisión"), "Riesgo Medio", TRUE, "Riesgo Bajo"), "Sin Dato") -> Riesgo Medio
A11: CLI-0822 | B11: 22.476.077-K | C11: Álvaro López Vergara | D11: álv.lópez@servicios.cl | E11: Valparaíso | F11: Valparaíso | G11: Región de Valparaíso | H11: 7680000 | I11: 45 | J11: Activo | K11: 46164 | L11: Crédito Estudios | N11: =PROPER(TRIM(C11)) -> Álvaro López Vergara | O11: =TRIM(B11) -> 22.476.077-K | P11: =TEXTJOIN(" - ", TRUE, E11, F11, G11) -> Valparaíso - Valparaíso - Región de Valparaíso | Q11: =PROPER(J11) -> Activo | R11: =IFERROR(IFS(AND(I11>60, Q11="Activo"), "Riesgo Alto", OR(I11>30, Q11="En Revisión"), "Riesgo Medio", TRUE, "Riesgo Bajo"), "Sin Dato") -> Riesgo Medio
A12: CLI-0604 | B12: 13776102-7 | C12: Álvaro Morales López | D12: álv.morales@gmail.com | E12: Valparaíso | F12: Valparaíso | G12: Región de Valparaíso | H12: 11050000 | I12: 0 | J12: Inactivo | K12: 46031 | L12: Crédito Automotriz | N12: =PROPER(TRIM(C12)) -> Álvaro Morales López | O12: =TRIM(B12) -> 13776102-7 | P12: =TEXTJOIN(" - ", TRUE, E12, F12, G12) -> Valparaíso - Valparaíso - Región de Valparaíso | Q12: =PROPER(J12) -> Inactivo | R12: =IFERROR(IFS(AND(I12>60, Q12="Activo"), "Riesgo Alto", OR(I12>30, Q12="En Revisión"), "Riesgo Medio", TRUE, "Riesgo Bajo"), "Sin Dato") -> Riesgo Bajo
A13: CLI-0842 | B13: 20.297.968-3 | C13: Álvaro Muñoz Sepúlveda | D13: álv.muñoz@outlook.cl | E13: Las Condes | F13: Santiago | G13: Región Metropolitana | H13: 7440000 | I13: 60 | J13: Inactivo | K13: 46153 | L13: Hipotecario | N13: =PROPER(TRIM(C13)) -> Álvaro Muñoz Sepúlveda | O13: =TRIM(B13) -> 20.297.968-3 | P13: =TEXTJOIN(" - ", TRUE, E13, F13, G13) -> Las Condes - Santiago - Región Metropolitana | Q13: =PROPER(J13) -> Inactivo | R13: =IFERROR(IFS(AND(I13>60, Q13="Activo"), "Riesgo Alto", OR(I13>30, Q13="En Revisión"), "Riesgo Medio", TRUE, "Riesgo Bajo"), "Sin Dato") -> Riesgo Medio
A14: CLI-0012 | B14: 19.537.899-0 | C14: Álvaro Pérez Soto | D14: álv.pérez@consultora.cl | E14: Concepción | F14: Concepción | G14: Región del Biobío | H14: 14910000 | I14: 120 | J14: En Revisión | K14: 46209 | L14: Crédito Estudios | N14: =PROPER(TRIM(C14)) -> Álvaro Pérez Soto | O14: =TRIM(B14) -> 19.537.899-0 | P14: =TEXTJOIN(" - ", TRUE, E14, F14, G14) -> Concepción - Concepción - Región del Biobío | Q14: =PROPER(J14) -> En Revisión | R14: =IFERROR(IFS(AND(I14>60, Q14="Activo"), "Riesgo Alto", OR(I14>30, Q14="En Revisión"), "Riesgo Medio", TRUE, "Riesgo Bajo"), "Sin Dato") -> Riesgo Medio
A15: CLI-0536 | B15: 17.286.867-9 | C15: Álvaro Pérez Vergara | D15: álv.pérez@gmail.com | E15: Antofagasta | F15: Antofagasta | G15: Región de Antofagasta | H15: 21220000 | I15: 0 | J15: Activo | K15: 46094 | L15: Línea Débito | N15: =PROPER(TRIM(C15)) -> Álvaro Pérez Vergara | O15: =TRIM(B15) -> 17.286.867-9 | P15: =TEXTJOIN(" - ", TRUE, E15, F15, G15) -> Antofagasta - Antofagasta - Región de Antofagasta | Q15: =PROPER(J15) -> Activo | R15: =IFERROR(IFS(AND(I15>60, Q15="Activo"), "Riesgo Alto", OR(I15>30, Q15="En Revisión"), "Riesgo Medio", TRUE, "Riesgo Bajo"), "Sin Dato") -> Riesgo Bajo
A16: CLI-0792 | B16: 13.189.660-2 | C16: Álvaro Rodríguez Rodríguez | D16: álv.rodríguez@consultora.cl | E16: Maipú | F16: Santiago | G16: Región Metropolitana | H16: 3080000 | I16: 30 | J16: En Revisión | K16: 46129 | L16: Línea Débito | N16: =PROPER(TRIM(C16)) -> Álvaro Rodríguez Rodríguez | O16: =TRIM(B16) -> 13.189.660-2 | P16: =TEXTJOIN(" - ", TRUE, E16, F16, G16) -> Maipú - Santiago - Región Metropolitana | Q16: =PROPER(J16) -> En Revisión | R16: =IFERROR(IFS(AND(I16>60, Q16="Activo"), "Riesgo Alto", OR(I16>30, Q16="En Revisión"), "Riesgo Medio", TRUE, "Riesgo Bajo"), "Sin Dato") -> Riesgo Medio
... A957: CLI-0487 | B957: 17.871.403-2 | C957: Valentina Valenzuela Araya | D957: val.valenzuela@gmail.com | E957: Valparaíso | F957: Valparaíso | G957: Región de Valparaíso | H957: 17680000 | I957: 45 | J957: Activo | K957: 46205 | L957: Crédito Automotriz | N957: =PROPER(TRIM(C957)) -> Valentina Valenzuela Araya | O957: =TRIM(B957) -> 17.871.403-2 | P957: =TEXTJOIN(" - ", TRUE, E957, F957, G957) -> Valparaíso - Valparaíso - Región de Valparaíso | Q957: =PROPER(J957) -> Activo | R957: =IFERROR(IFS(AND(I957>60, Q957="Activo"), "Riesgo Alto", OR(I957>30, Q957="En Revisión"), "Riesgo Medio", TRUE, "Riesgo Bajo"), "Sin Dato") -> Riesgo Medio

Sheet Hoja 10
I1: Ingresos totales Facturados | J1: =SUM(Dataset_limpio_A2!H2:H957) -> 11090210000

Sheet Tabla dinámica

Sheet 2.10_A3_Ventas
A1: ID_Transaccion | B1: Fecha_Venta | C1: ID_Cliente | D1: ID_Producto | E1: ID_Sucursal | F1: Cantidad | H1: Buscar ID | I1: Resultado | J1: Explicación
A2: TRX-2072 | B2: 46145 | C2: CLI-001 | D2: PROD-115 | E2: SUC-10 | F2: 1 | H2: CLI-001 | I2: {=IFERROR(_xlfn.XLOOKUP(H2, '2.10 Clientes'!A$2:A$101, '2.10 Clientes'!C$2:C$101), "No encontrado")} -> Catalina López Espinoza | J2: Linkeando los clientes desde la pagina de clientes funciona, aunque son datos independientes no los tomaba
A3: TRX-2100 | B3: 46221 | C3: CLI-001 | D3: PROD-999 | E3: SUC-10 | F3: 3 | H3: CLI-002 | I3: {=IFERROR(_xlfn.XLOOKUP(H3, '2.10 Clientes'!A$2:A$101, '2.10 Clientes'!C$2:C$101), "No encontrado")} -> Claudio Silva Muñoz
A4: TRX-2144 | B4: 46040 | C4: CLI-001 | D4: PROD-104 | E4: SUC-10 | F4: 3 | H4: CLI-003 | I4: {=IFERROR(_xlfn.XLOOKUP(H4, '2.10 Clientes'!A$2:A$101, '2.10 Clientes'!C$2:C$101), "No encontrado")} -> Valentina Valenzuela Morales
A5: TRX-2161 | B5: 46216 | C5: CLI-001 | D5: PROD-121 | E5: SUC-04 | F5: 1
A6: TRX-2196 | B6: 46049 | C6: CLI-001 | D6: PROD-105 | E6: SUC-06 | F6: 5
A7: TRX-2271 | B7: 46127 | C7: CLI-001 | D7: PROD-119 | E7: SUC-06 | F7: 3 | H7: ID | I7: Nombre producto | J7: Precio Unitario CLP
A8: TRX-2243 | B8: 46150 | C8: CLI-002 | D8: PROD-122 | E8: SUC-14 | F8: 5 | H8: PROD-125 | I8: {=IFERROR(_xlfn.XLOOKUP(H8, '2.10_Productos'!A$2:A$26, '2.10_Productos'!B$2:B$26), "No encontrado")} -> Configuración SD-WAN Redes | J8: {=IFERROR(_xlfn.XLOOKUP(H8, '2.10_Productos'!A$2:A$26, '2.10_Productos'!D$2:D$26), "No encontrado")} -> 1250000
A9: TRX-2073 | B9: 46211 | C9: CLI-003 | D9: PROD-119 | E9: SUC-15 | F9: 5
A10: TRX-2104 | B10: 46197 | C10: CLI-003 | D10: PROD-110 | E10: SUC-11 | F10: 10
A11: TRX-2203 | B11: 46096 | C11: CLI-003 | D11: PROD-123 | E11: SUC-12 | F11: 10
A12: TRX-2097 | B12: 46038 | C12: CLI-004 | D12: PROD-104 | E12: SUC-11 | F12: 2
A13: TRX-2174 | B13: 46114 | C13: CLI-004 | D13: PROD-124 | E13: SUC-08 | F13: 5
A14: TRX-2197 | B14: 46219 | C14: CLI-004 | D14: PROD-118 | E14: SUC-10 | F14: 5
A15: TRX-2260 | B15: 46077 | C15: CLI-004 | D15: PROD-114 | E15: SUC-04 | F15: 5
A16: TRX-2287 | B16: 46137 | C16: CLI-004 | D16: PROD-103 | E16: SUC-12 | F16: 5
A17: TRX-2154 | B17: 46231 | C17: CLI-005 | D17: PROD-117 | E17: SUC-04 | F17: 10
A18: TRX-2171 | B18: 46085 | C18: CLI-005 | D18: PROD-102 | E18: SUC-04 | F18: 10
A19: TRX-2215 | B19: 46128 | C19: CLI-005 | D19: PROD-117 | E19: SUC-10 | F19: 10
A20: TRX-2267 | B20: 46229 | C20: CLI-005 | D20: PROD-120 | E20: SUC-07 | F20: 5
... A301: TRX-2150 | B301: 46102 | C301: CLI-999 | D301: PROD-118 | E301: SUC-11 | F301: 3

Sheet Tabla dinámica 7

Sheet 2.10 Clientes
A1: ID_Cliente | B1: RUT_Cliente | C1: Nombre_Cliente | D1: Segmento | E1: Comuna | F1: Ciudad | G1: Region
A2: CLI-001 | B2: 18.768.710-6 | C2: Catalina López Espinoza | D2: Persona | E2: Puerto Montt | F2: Puerto Montt | G2: Región de Los Lagos
A3: CLI-002 | B3: 22.115.701-8 | C3: Claudio Silva Muñoz | D3: Persona | E3: Valparaíso | F3: Valparaíso | G3: Región de Valparaíso
A4: CLI-003 | B4: 13.069.307-8 | C4: Valentina Valenzuela Morales | D4: VIP | E4: Concepción | F4: Concepción | G4: Región del Biobío
A5: CLI-004 | B5: 20.062.876-7 | C5: Rodrigo Espinoza Soto | D5: Persona | E5: Puerto Montt | F5: Puerto Montt | G5: Región de Los Lagos
A6: CLI-005 | B6: 18.001.798-K | C6: Camila López Muñoz | D6: Pyme | E6: Valparaíso | F6: Valparaíso | G6: Región de Valparaíso
A7: CLI-006 | B7: 13.692.229-3 | C7: Hernán Díaz Valenzuela | D7: Persona | E7: Talcahuano | F7: Concepción | G7: Región del Biobío
A8: CLI-007 | B8: 11.234.208-0 | C8: Carolina Valenzuela López | D8: Pyme | E8: Valparaíso | F8: Valparaíso | G8: Región de Valparaíso
A9: CLI-008 | B9: 17.229.320-4 | C9: Matías Morales Sepúlveda | D9: Corporativo | E9: Concepción | F9: Concepción | G9: Región del Biobío
A10: CLI-009 | B10: 20.777.271-5 | C10: Andrea Muñoz Contreras | D10: Corporativo | E10: Viña del Mar | F10: Valparaíso | G10: Región de Valparaíso
A11: CLI-010 | B11: 16.604.616-4 | C11: Felipe Pérez Espinoza | D11: VIP | E11: Antofagasta | F11: Antofagasta | G11: Región de Antofagasta
A12: CLI-011 | B12: 14.834.321-1 | C12: Paula Espinoza Silva | D12: VIP | E12: Valparaíso | F12: Valparaíso | G12: Región de Valparaíso
... A101: CLI-100 | B101: 19.042.900-K | C101: Esteban Araya Valenzuela | D101: VIP | E101: La Serena | F101: La Serena | G101: Región de Coquimbo

Sheet 2.10_Productos
A1: ID_Producto | B1: Nombre_Producto | C1: Categoria | D1: Precio_Unitario_CLP
A2: PROD-101 | B2: Licencia ERP Cloud Pro | C2: Software | D2: 950000
A3: PROD-102 | B3: Licencia CRM Enterprise | C3: Software | D3: 1350000
A4: PROD-103 | B4: Consultoría Migración Data 20h | C4: Consultoría | D4: 1450000
A5: PROD-104 | B5: Auditoría Ciberseguridad Pentest | C5: Seguridad | D5: 2800000
A6: PROD-105 | B6: Mantenimiento Servidores 24/7 | C6: Infraestructura | D6: 1100000
A7: PROD-106 | B7: Laptop Pro i7 32GB RAM | C7: Hardware | D7: 1450000
A8: PROD-107 | B8: Monitor 32 Pulgadas 4K HDR | C8: Hardware | D8: 490000
A9: PROD-108 | B9: Licencia Business Intelligence Pro | C9: Software | D9: 980000
A10: PROD-109 | B10: Servicio Backup Automatizado Cloud | C10: Seguridad | D10: 620000
A11: PROD-110 | B11: Firewall Corporativo 10Gbps | C11: Seguridad | D11: 4200000
A12: PROD-111 | B12: Servidor Rack Enterprise 4U | C12: Infraestructura | D12: 5900000
A13: PROD-112 | B13: Kit Ergónomico Teclado+Mouse | C13: Hardware | D13: 85000
... A26: PROD-125 | B26: Configuración SD-WAN Redes | C26: Consultoría | D26: 1250000

Sheet 2.10_A3_Sucursales
A1: ID_Sucursal | B1: Nombre_Sucursal | C1: Comuna | D1: Ciudad | E1: Zona_Comercial
A2: SUC-01 | B2: Sucursal Las Condes | C2: Las Condes | D2: Santiago | E2: Zona Oriente
A3: SUC-02 | B3: Sucursal Providencia | C3: Providencia | D3: Santiago | E3: Zona Oriente
A4: SUC-03 | B4: Sucursal Santiago Centro | C4: Santiago Centro | D4: Santiago | E4: Zona Centro
A5: SUC-04 | B5: Sucursal Viña del Mar | C5: Viña del Mar | D5: Valparaíso | E5: Zona Costa Norte
A6: SUC-05 | B6: Sucursal Concepción Centro | C6: Concepción | D6: Concepción | E6: Zona Sur
A7: SUC-06 | B7: Sucursal Antofagasta Costa | C7: Antofagasta | D7: Antofagasta | E7: Zona Norte
A8: SUC-07 | B8: Sucursal Temuco | C8: Temuco | D8: Temuco | E8: Zona Sur
A9: SUC-08 | B9: Sucursal Puerto Montt | C9: Puerto Montt | D9: Puerto Montt | E9: Zona Austral
A10: SUC-09 | B10: Sucursal La Serena | C10: La Serena | D10: La Serena | E10: Zona Norte
A11: SUC-10 | B11: Sucursal Ñuñoa | C11: Ñuñoa | D11: Santiago | E11: Zona Oriente
A12: SUC-11 | B12: Sucursal Maipú | C12: Maipú | D12: Santiago | E12: Zona Poniente
... A16: SUC-15 | B16: Sucursal Iquique | C16: Iquique | D16: Iquique | E16: Zona Norte Extremo

Sheet Consulta_Dinamica
A1: ID_Cliente | B1: RUT_Cliente | C1: Nombre_Completo | D1: Email_Contacto | E1: Comuna | F1: Ciudad | G1: Region | H1: Monto_Facturado_CLP | J1: Zonas Comerciales
A2: =IFERROR(__xludf.DUMMYFUNCTION("SORT(FILTER(Dataset_limpio_A2!A2:H1001, Dataset_limpio_A2!G2:G1001=""Región Metropolitana"", Dataset_limpio_A2!H2:H1001>1000000), 8, FALSE)"),"CLI-0930") -> CLI-0930 | B2: =IFERROR(__xludf.DUMMYFUNCTION("""COMPUTED_VALUE"""),"14.652.289-K") -> 14.652.289-K | C2: =IFERROR(__xludf.DUMMYFUNCTION("""COMPUTED_VALUE"""),"Matías Rojas Espinoza") -> Matías Rojas Espinoza | D2: =IFERROR(__xludf.DUMMYFUNCTION("""COMPUTED_VALUE"""),"mat.rojas@servicios.cl") -> mat.rojas@servicios.cl | E2: =IFERROR(__xludf.DUMMYFUNCTION("""COMPUTED_VALUE"""),"Las Condes") -> Las Condes | F2: =IFERROR(__xludf.DUMMYFUNCTION("""COMPUTED_VALUE"""),"Santiago") -> Santiago | G2: =IFERROR(__xludf.DUMMYFUNCTION("""COMPUTED_VALUE"""),"Región Metropolitana") -> Región Metropolitana | H2: =IFERROR(__xludf.DUMMYFUNCTION("""COMPUTED_VALUE"""),2.2E7) -> 22000000 | J2: {=UNIQUE(Dataset_limpio_A2!E$2:E$1000)} -> Talcahuano
A3: =IFERROR(__xludf.DUMMYFUNCTION("""COMPUTED_VALUE"""),"CLI-0526") -> CLI-0526 | B3: =IFERROR(__xludf.DUMMYFUNCTION("""COMPUTED_VALUE"""),"15.570.317-9") -> 15.570.317-9 | C3: =IFERROR(__xludf.DUMMYFUNCTION("""COMPUTED_VALUE"""),"Diego Araya Morales") -> Diego Araya Morales | D3: =IFERROR(__xludf.DUMMYFUNCTION("""COMPUTED_VALUE"""),"die.araya@gmail.com") -> die.araya@gmail.com | E3: =IFERROR(__xludf.DUMMYFUNCTION("""COMPUTED_VALUE"""),"Las Condes") -> Las Condes | F3: =IFERROR(__xludf.DUMMYFUNCTION("""COMPUTED_VALUE"""),"Santiago") -> Santiago | G3: =IFERROR(__xludf.DUMMYFUNCTION("""COMPUTED_VALUE"""),"Región Metropolitana") -> Región Metropolitana | H3: =IFERROR(__xludf.DUMMYFUNCTION("""COMPUTED_VALUE"""),2.193E7) -> 21930000 | J3: Antofagasta
A4: =IFERROR(__xludf.DUMMYFUNCTION("""COMPUTED_VALUE"""),"CLI-0658") -> CLI-0658 | B4: =IFERROR(__xludf.DUMMYFUNCTION("""COMPUTED_VALUE"""),"19.527.046-6") -> 19.527.046-6 | C4: =IFERROR(__xludf.DUMMYFUNCTION("""COMPUTED_VALUE"""),"Matías Muñoz Fuentes") -> Matías Muñoz Fuentes | D4: =IFERROR(__xludf.DUMMYFUNCTION("""COMPUTED_VALUE"""),"mat.muñoz@gmail.com") -> mat.muñoz@gmail.com | E4: =IFERROR(__xludf.DUMMYFUNCTION("""COMPUTED_VALUE"""),"Santiago Centro") -> Santiago Centro | F4: =IFERROR(__xludf.DUMMYFUNCTION("""COMPUTED_VALUE"""),"Santiago") -> Santiago | G4: =IFERROR(__xludf.DUMMYFUNCTION("""COMPUTED_VALUE"""),"Región Metropolitana") -> Región Metropolitana | H4: =IFERROR(__xludf.DUMMYFUNCTION("""COMPUTED_VALUE"""),2.192E7) -> 21920000 | J4: Puerto Montt
A5: =IFERROR(__xludf.DUMMYFUNCTION("""COMPUTED_VALUE"""),"CLI-0040") -> CLI-0040 | B5: =IFERROR(__xludf.DUMMYFUNCTION("""COMPUTED_VALUE"""),"19.552.605-0") -> 19.552.605-0 | C5: =IFERROR(__xludf.DUMMYFUNCTION("""COMPUTED_VALUE"""),"Sebastián Díaz Araya") -> Sebastián Díaz Araya | D5: =IFERROR(__xludf.DUMMYFUNCTION("""COMPUTED_VALUE"""),"seb.díaz@outlook.cl") -> seb.díaz@outlook.cl | E5: =IFERROR(__xludf.DUMMYFUNCTION("""COMPUTED_VALUE"""),"Ñuñoa") -> Ñuñoa | F5: =IFERROR(__xludf.DUMMYFUNCTION("""COMPUTED_VALUE"""),"Santiago") -> Santiago | G5: =IFERROR(__xludf.DUMMYFUNCTION("""COMPUTED_VALUE"""),"Región Metropolitana") -> Región Metropolitana | H5: =IFERROR(__xludf.DUMMYFUNCTION("""COMPUTED_VALUE"""),2.178E7) -> 21780000 | J5: Las Condes
A6: =IFERROR(__xludf.DUMMYFUNCTION("""COMPUTED_VALUE"""),"CLI-0282") -> CLI-0282 | B6: =IFERROR(__xludf.DUMMYFUNCTION("""COMPUTED_VALUE"""),"17.108.951-7") -> 17.108.951-7 | C6: =IFERROR(__xludf.DUMMYFUNCTION("""COMPUTED_VALUE"""),"Rodrigo López Soto") -> Rodrigo López Soto | D6: =IFERROR(__xludf.DUMMYFUNCTION("""COMPUTED_VALUE"""),"rod.lópez@empresa.cl") -> rod.lópez@empresa.cl | E6: =IFERROR(__xludf.DUMMYFUNCTION("""COMPUTED_VALUE"""),"Ñuñoa") -> Ñuñoa | F6: =IFERROR(__xludf.DUMMYFUNCTION("""COMPUTED_VALUE"""),"Santiago") -> Santiago | G6: =IFERROR(__xludf.DUMMYFUNCTION("""COMPUTED_VALUE"""),"Región Metropolitana") -> Región Metropolitana | H6: =IFERROR(__xludf.DUMMYFUNCTION("""COMPUTED_VALUE"""),2.174E7) -> 21740000 | J6: La Serena
A7: =IFERROR(__xludf.DUMMYFUNCTION("""COMPUTED_VALUE"""),"CLI-0455") -> CLI-0455 | B7: =IFERROR(__xludf.DUMMYFUNCTION("""COMPUTED_VALUE"""),"12.842.943-K") -> 12.842.943-K | C7: =IFERROR(__xludf.DUMMYFUNCTION("""COMPUTED_VALUE"""),"Constanza Muñoz López") -> Constanza Muñoz López | D7: =IFERROR(__xludf.DUMMYFUNCTION("""COMPUTED_VALUE"""),"con.muñoz@sura.cl") -> con.muñoz@sura.cl | E7: =IFERROR(__xludf.DUMMYFUNCTION("""COMPUTED_VALUE"""),"Maipú") -> Maipú | F7: =IFERROR(__xludf.DUMMYFUNCTION("""COMPUTED_VALUE"""),"Santiago") -> Santiago | G7: =IFERROR(__xludf.DUMMYFUNCTION("""COMPUTED_VALUE"""),"Región Metropolitana") -> Región Metropolitana | H7: =IFERROR(__xludf.DUMMYFUNCTION("""COMPUTED_VALUE"""),2.173E7) -> 21730000 | J7: Valparaíso
A8: =IFERROR(__xludf.DUMMYFUNCTION("""COMPUTED_VALUE"""),"CLI-0427") -> CLI-0427 | B8: =IFERROR(__xludf.DUMMYFUNCTION("""COMPUTED_VALUE"""),"19.079.232-2") -> 19.079.232-2 | C8: =IFERROR(__xludf.DUMMYFUNCTION("""COMPUTED_VALUE"""),"Beatriz Araya Valenzuela") -> Beatriz Araya Valenzuela | D8: =IFERROR(__xludf.DUMMYFUNCTION("""COMPUTED_VALUE"""),"bea.araya@consultora.cl") -> bea.araya@consultora.cl | E8: =IFERROR(__xludf.DUMMYFUNCTION("""COMPUTED_VALUE"""),"Maipú") -> Maipú | F8: =IFERROR(__xludf.DUMMYFUNCTION("""COMPUTED_VALUE"""),"Santiago") -> Santiago | G8: =IFERROR(__xludf.DUMMYFUNCTION("""COMPUTED_VALUE"""),"Región Metropolitana") -> Región Metropolitana | H8: =IFERROR(__xludf.DUMMYFUNCTION("""COMPUTED_VALUE"""),2.154E7) -> 21540000 | J8: Santiago Centro
A9: =IFERROR(__xludf.DUMMYFUNCTION("""COMPUTED_VALUE"""),"CLI-0214") -> CLI-0214 | B9: =IFERROR(__xludf.DUMMYFUNCTION("""COMPUTED_VALUE"""),"13.544.045-8") -> 13.544.045-8 | C9: =IFERROR(__xludf.DUMMYFUNCTION("""COMPUTED_VALUE"""),"Tomas González Silva") -> Tomas González Silva | D9: =IFERROR(__xludf.DUMMYFUNCTION("""COMPUTED_VALUE"""),"tom.gonzález@outlook.cl") -> tom.gonzález@outlook.cl | E9: =IFERROR(__xludf.DUMMYFUNCTION("""COMPUTED_VALUE"""),"Santiago Centro") -> Santiago Centro | F9: =IFERROR(__xludf.DUMMYFUNCTION("""COMPUTED_VALUE"""),"Santiago") -> Santiago | G9: =IFERROR(__xludf.DUMMYFUNCTION("""COMPUTED_VALUE"""),"Región Metropolitana") -> Región Metropolitana | H9: =IFERROR(__xludf.DUMMYFUNCTION("""COMPUTED_VALUE"""),2.154E7) -> 21540000 | J9: Maipú
A10: =IFERROR(__xludf.DUMMYFUNCTION("""COMPUTED_VALUE"""),"CLI-0022") -> CLI-0022 | B10: =IFERROR(__xludf.DUMMYFUNCTION("""COMPUTED_VALUE"""),"12.322.581-5") -> 12.322.581-5 | C10: =IFERROR(__xludf.DUMMYFUNCTION("""COMPUTED_VALUE"""),"Rodrigo Valenzuela Espinoza") -> Rodrigo Valenzuela Espinoza | D10: =IFERROR(__xludf.DUMMYFUNCTION("""COMPUTED_VALUE"""),"rod.valenzuela@gmail.com") -> rod.valenzuela@gmail.com | E10: =IFERROR(__xludf.DUMMYFUNCTION("""COMPUTED_VALUE"""),"Maipú") -> Maipú | F10: =IFERROR(__xludf.DUMMYFUNCTION("""COMPUTED_VALUE"""),"Santiago") -> Santiago | G10: =IFERROR(__xludf.DUMMYFUNCTION("""COMPUTED_VALUE"""),"Región Metropolitana") -> Región Metropolitana | H10: =IFERROR(__xludf.DUMMYFUNCTION("""COMPUTED_VALUE"""),2.145E7) -> 21450000 | J10: Concepción
A11: =IFERROR(__xludf.DUMMYFUNCTION("""COMPUTED_VALUE"""),"CLI-0907") -> CLI-0907 | B11: =IFERROR(__xludf.DUMMYFUNCTION("""COMPUTED_VALUE"""),"18595218-3") -> 18595218-3 | C11: =IFERROR(__xludf.DUMMYFUNCTION("""COMPUTED_VALUE"""),"Catalina Morales Rojas") -> Catalina Morales Rojas | D11: =IFERROR(__xludf.DUMMYFUNCTION("""COMPUTED_VALUE"""),"cat.morales@servicios.cl") -> cat.morales@servicios.cl | E11: =IFERROR(__xludf.DUMMYFUNCTION("""COMPUTED_VALUE"""),"Las Condes") -> Las Condes | F11: =IFERROR(__xludf.DUMMYFUNCTION("""COMPUTED_VALUE"""),"Santiago") -> Santiago | G11: =IFERROR(__xludf.DUMMYFUNCTION("""COMPUTED_VALUE"""),"Región Metropolitana") -> Región Metropolitana | H11: =IFERROR(__xludf.DUMMYFUNCTION("""COMPUTED_VALUE"""),2.142E7) -> 21420000 | J11: Viña del Mar
A12: =IFERROR(__xludf.DUMMYFUNCTION("""COMPUTED_VALUE"""),"CLI-0390") -> CLI-0390 | B12: =IFERROR(__xludf.DUMMYFUNCTION("""COMPUTED_VALUE"""),"13.709.077-9") -> 13.709.077-9 | C12: =IFERROR(__xludf.DUMMYFUNCTION("""COMPUTED_VALUE"""),"Cristián Soto Tapia") -> Cristián Soto Tapia | D12: =IFERROR(__xludf.DUMMYFUNCTION("""COMPUTED_VALUE"""),"cri.soto@gmail.com") -> cri.soto@gmail.com | E12: =IFERROR(__xludf.DUMMYFUNCTION("""COMPUTED_VALUE"""),"Las Condes") -> Las Condes | F12: =IFERROR(__xludf.DUMMYFUNCTION("""COMPUTED_VALUE"""),"Santiago") -> Santiago | G12: =IFERROR(__xludf.DUMMYFUNCTION("""COMPUTED_VALUE"""),"Región Metropolitana") -> Región Metropolitana | H12: =IFERROR(__xludf.DUMMYFUNCTION("""COMPUTED_VALUE"""),2.138E7) -> 21380000 | J12: Temuco
A13: =IFERROR(__xludf.DUMMYFUNCTION("""COMPUTED_VALUE"""),"CLI-0119") -> CLI-0119 | B13: =IFERROR(__xludf.DUMMYFUNCTION("""COMPUTED_VALUE"""),"11964091-1") -> 11964091-1 | C13: =IFERROR(__xludf.DUMMYFUNCTION("""COMPUTED_VALUE"""),"Marcela Pérez Fuentes") -> Marcela Pérez Fuentes | D13: =IFERROR(__xludf.DUMMYFUNCTION("""COMPUTED_VALUE"""),"mar.pérez@servicios.cl") -> mar.pérez@servicios.cl | E13: =IFERROR(__xludf.DUMMYFUNCTION("""COMPUTED_VALUE"""),"Santiago Centro") -> Santiago Centro | F13: =IFERROR(__xludf.DUMMYFUNCTION("""COMPUTED_VALUE"""),"Santiago") -> Santiago | G13: =IFERROR(__xludf.DUMMYFUNCTION("""COMPUTED_VALUE"""),"Región Metropolitana") -> Región Metropolitana | H13: =IFERROR(__xludf.DUMMYFUNCTION("""COMPUTED_VALUE"""),2.119E7) -> 21190000 | J13: Ñuñoa
A14: =IFERROR(__xludf.DUMMYFUNCTION("""COMPUTED_VALUE"""),"CLI-0570") -> CLI-0570 | B14: =IFERROR(__xludf.DUMMYFUNCTION("""COMPUTED_VALUE"""),"21384372-2") -> 21384372-2 | C14: =IFERROR(__xludf.DUMMYFUNCTION("""COMPUTED_VALUE"""),"Álvaro Tapia Morales") -> Álvaro Tapia Morales | D14: =IFERROR(__xludf.DUMMYFUNCTION("""COMPUTED_VALUE"""),"álv.tapia@gmail.com") -> álv.tapia@gmail.com | E14: =IFERROR(__xludf.DUMMYFUNCTION("""COMPUTED_VALUE"""),"Maipú") -> Maipú | F14: =IFERROR(__xludf.DUMMYFUNCTION("""COMPUTED_VALUE"""),"Santiago") -> Santiago | G14: =IFERROR(__xludf.DUMMYFUNCTION("""COMPUTED_VALUE"""),"Región Metropolitana") -> Región Metropolitana | H14: =IFERROR(__xludf.DUMMYFUNCTION("""COMPUTED_VALUE"""),2.106E7) -> 21060000 | J14: Providencia
A15: =IFERROR(__xludf.DUMMYFUNCTION("""COMPUTED_VALUE"""),"CLI-0805") -> CLI-0805 | B15: =IFERROR(__xludf.DUMMYFUNCTION("""COMPUTED_VALUE"""),"16259379-5") -> 16259379-5 | C15: =IFERROR(__xludf.DUMMYFUNCTION("""COMPUTED_VALUE"""),"Sofia Fuentes López") -> Sofia Fuentes López | D15: =IFERROR(__xludf.DUMMYFUNCTION("""COMPUTED_VALUE"""),"sof.fuentes@servicios.cl") -> sof.fuentes@servicios.cl | E15: =IFERROR(__xludf.DUMMYFUNCTION("""COMPUTED_VALUE"""),"Santiago Centro") -> Santiago Centro | F15: =IFERROR(__xludf.DUMMYFUNCTION("""COMPUTED_VALUE"""),"Santiago") -> Santiago | G15: =IFERROR(__xludf.DUMMYFUNCTION("""COMPUTED_VALUE"""),"Región Metropolitana") -> Región Metropolitana | H15: =IFERROR(__xludf.DUMMYFUNCTION("""COMPUTED_VALUE"""),2.106E7) -> 21060000
A16: =IFERROR(__xludf.DUMMYFUNCTION("""COMPUTED_VALUE"""),"CLI-0096") -> CLI-0096 | B16: =IFERROR(__xludf.DUMMYFUNCTION("""COMPUTED_VALUE"""),"12.265.019-7") -> 12.265.019-7 | C16: =IFERROR(__xludf.DUMMYFUNCTION("""COMPUTED_VALUE"""),"Sebastián Tapia Muñoz") -> Sebastián Tapia Muñoz | D16: =IFERROR(__xludf.DUMMYFUNCTION("""COMPUTED_VALUE"""),"seb.tapia@empresa.cl") -> seb.tapia@empresa.cl | E16: =IFERROR(__xludf.DUMMYFUNCTION("""COMPUTED_VALUE"""),"Providencia") -> Providencia | F16: =IFERROR(__xludf.DUMMYFUNCTION("""COMPUTED_VALUE"""),"Santiago") -> Santiago | G16: =IFERROR(__xludf.DUMMYFUNCTION("""COMPUTED_VALUE"""),"Región Metropolitana") -> Región Metropolitana | H16: =IFERROR(__xludf.DUMMYFUNCTION("""COMPUTED_VALUE"""),2.086E7) -> 20860000
A17: =IFERROR(__xludf.DUMMYFUNCTION("""COMPUTED_VALUE"""),"CLI-0793") -> CLI-0793 | B17: =IFERROR(__xludf.DUMMYFUNCTION("""COMPUTED_VALUE"""),"16.198.351-5") -> 16.198.351-5 | C17: =IFERROR(__xludf.DUMMYFUNCTION("""COMPUTED_VALUE"""),"Catalina López Fuentes") -> Catalina López Fuentes | D17: =IFERROR(__xludf.DUMMYFUNCTION("""COMPUTED_VALUE"""),"cat.lópez@outlook.cl") -> cat.lópez@outlook.cl | E17: =IFERROR(__xludf.DUMMYFUNCTION("""COMPUTED_VALUE"""),"Las Condes") -> Las Condes | F17: =IFERROR(__xludf.DUMMYFUNCTION("""COMPUTED_VALUE"""),"Santiago") -> Santiago | G17: =IFERROR(__xludf.DUMMYFUNCTION("""COMPUTED_VALUE"""),"Región Metropolitana") -> Región Metropolitana | H17: =IFERROR(__xludf.DUMMYFUNCTION("""COMPUTED_VALUE"""),2.085E7) -> 20850000
A18: =IFERROR(__xludf.DUMMYFUNCTION("""COMPUTED_VALUE"""),"CLI-0783") -> CLI-0783 | B18: =IFERROR(__xludf.DUMMYFUNCTION("""COMPUTED_VALUE"""),"16.766.254-5") -> 16.766.254-5 | C18: =IFERROR(__xludf.DUMMYFUNCTION("""COMPUTED_VALUE"""),"Sofia Espinoza Espinoza") -> Sofia Espinoza Espinoza | D18: =IFERROR(__xludf.DUMMYFUNCTION("""COMPUTED_VALUE"""),"sof.espinoza@consultora.cl") -> sof.espinoza@consultora.cl | E18: =IFERROR(__xludf.DUMMYFUNCTION("""COMPUTED_VALUE"""),"Ñuñoa") -> Ñuñoa | F18: =IFERROR(__xludf.DUMMYFUNCTION("""COMPUTED_VALUE"""),"Santiago") -> Santiago | G18: =IFERROR(__xludf.DUMMYFUNCTION("""COMPUTED_VALUE"""),"Región Metropolitana") -> Región Metropolitana | H18: =IFERROR(__xludf.DUMMYFUNCTION("""COMPUTED_VALUE"""),2.079E7) -> 20790000
A19: =IFERROR(__xludf.DUMMYFUNCTION("""COMPUTED_VALUE"""),"CLI-0696") -> CLI-0696 | B19: =IFERROR(__xludf.DUMMYFUNCTION("""COMPUTED_VALUE"""),"19.743.139-4") -> 19.743.139-4 | C19: =IFERROR(__xludf.DUMMYFUNCTION("""COMPUTED_VALUE"""),"Rodrigo Fuentes Vergara") -> Rodrigo Fuentes Vergara | D19: =IFERROR(__xludf.DUMMYFUNCTION("""COMPUTED_VALUE"""),"rod.fuentes@outlook.cl") -> rod.fuentes@outlook.cl | E19: =IFERROR(__xludf.DUMMYFUNCTION("""COMPUTED_VALUE"""),"Ñuñoa") -> Ñuñoa | F19: =IFERROR(__xludf.DUMMYFUNCTION("""COMPUTED_VALUE"""),"Santiago") -> Santiago | G19: =IFERROR(__xludf.DUMMYFUNCTION("""COMPUTED_VALUE"""),"Región Metropolitana") -> Región Metropolitana | H19: =IFERROR(__xludf.DUMMYFUNCTION("""COMPUTED_VALUE"""),2.062E7) -> 20620000
A20: =IFERROR(__xludf.DUMMYFUNCTION("""COMPUTED_VALUE"""),"CLI-0194") -> CLI-0194 | B20: =IFERROR(__xludf.DUMMYFUNCTION("""COMPUTED_VALUE"""),"13.347.500-4") -> 13.347.500-4 | C20: =IFERROR(__xludf.DUMMYFUNCTION("""COMPUTED_VALUE"""),"Sebastián Sepúlveda Silva") -> Sebastián Sepúlveda Silva | D20: =IFERROR(__xludf.DUMMYFUNCTION("""COMPUTED_VALUE"""),"seb.sepúlveda@empresa.cl") -> seb.sepúlveda@empresa.cl | E20: =IFERROR(__xludf.DUMMYFUNCTION("""COMPUTED_VALUE"""),"Providencia") -> Providencia | F20: =IFERROR(__xludf.DUMMYFUNCTION("""COMPUTED_VALUE"""),"Santiago") -> Santiago | G20: =IFERROR(__xludf.DUMMYFUNCTION("""COMPUTED_VALUE"""),"Región Metropolitana") -> Región Metropolitana | H20: =IFERROR(__xludf.DUMMYFUNCTION("""COMPUTED_VALUE"""),2.057E7) -> 20570000
A21: =IFERROR(__xludf.DUMMYFUNCTION("""COMPUTED_VALUE"""),"CLI-0725") -> CLI-0725 | B21: =IFERROR(__xludf.DUMMYFUNCTION("""COMPUTED_VALUE"""),"16.481.237-2") -> 16.481.237-2 | C21: =IFERROR(__xludf.DUMMYFUNCTION("""COMPUTED_VALUE"""),"Valentina Rojas Vergara") -> Valentina Rojas Vergara | D21: =IFERROR(__xludf.DUMMYFUNCTION("""COMPUTED_VALUE"""),"val.rojas@empresa.cl") -> val.rojas@empresa.cl | E21: =IFERROR(__xludf.DUMMYFUNCTION("""COMPUTED_VALUE"""),"Ñuñoa") -> Ñuñoa | F21: =IFERROR(__xludf.DUMMYFUNCTION("""COMPUTED_VALUE"""),"Santiago") -> Santiago | G21: =IFERROR(__xludf.DUMMYFUNCTION("""COMPUTED_VALUE"""),"Región Metropolitana") -> Región Metropolitana | H21: =IFERROR(__xludf.DUMMYFUNCTION("""COMPUTED_VALUE"""),2.029E7) -> 20290000
A22: =IFERROR(__xludf.DUMMYFUNCTION("""COMPUTED_VALUE"""),"CLI-0209") -> CLI-0209 | B22: =IFERROR(__xludf.DUMMYFUNCTION("""COMPUTED_VALUE"""),"15.447.490-9") -> 15.447.490-9 | C22: =IFERROR(__xludf.DUMMYFUNCTION("""COMPUTED_VALUE"""),"Beatriz Araya Fuentes") -> Beatriz Araya Fuentes | D22: =IFERROR(__xludf.DUMMYFUNCTION("""COMPUTED_VALUE"""),"bea.araya@consultora.cl") -> bea.araya@consultora.cl | E22: =IFERROR(__xludf.DUMMYFUNCTION("""COMPUTED_VALUE"""),"Providencia") -> Providencia | F22: =IFERROR(__xludf.DUMMYFUNCTION("""COMPUTED_VALUE"""),"Santiago") -> Santiago | G22: =IFERROR(__xludf.DUMMYFUNCTION("""COMPUTED_VALUE"""),"Región Metropolitana") -> Región Metropolitana | H22: =IFERROR(__xludf.DUMMYFUNCTION("""COMPUTED_VALUE"""),2.025E7) -> 20250000
A23: =IFERROR(__xludf.DUMMYFUNCTION("""COMPUTED_VALUE"""),"CLI-0640") -> CLI-0640 | B23: =IFERROR(__xludf.DUMMYFUNCTION("""COMPUTED_VALUE"""),"15623137-7") -> 15623137-7 | C23: =IFERROR(__xludf.DUMMYFUNCTION("""COMPUTED_VALUE"""),"Gabriel Araya Rojas") -> Gabriel Araya Rojas | D23: =IFERROR(__xludf.DUMMYFUNCTION("""COMPUTED_VALUE"""),"gab.araya@servicios.cl") -> gab.araya@servicios.cl | E23: =IFERROR(__xludf.DUMMYFUNCTION("""COMPUTED_VALUE"""),"Maipú") -> Maipú | F23: =IFERROR(__xludf.DUMMYFUNCTION("""COMPUTED_VALUE"""),"Santiago") -> Santiago | G23: =IFERROR(__xludf.DUMMYFUNCTION("""COMPUTED_VALUE"""),"Región Metropolitana") -> Región Metropolitana | H23: =IFERROR(__xludf.DUMMYFUNCTION("""COMPUTED_VALUE"""),2.021E7) -> 20210000
A24: =IFERROR(__xludf.DUMMYFUNCTION("""COMPUTED_VALUE"""),"CLI-0716") -> CLI-0716 | B24: =IFERROR(__xludf.DUMMYFUNCTION("""COMPUTED_VALUE"""),"11.356.961-4") -> 11.356.961-4 | C24: =IFERROR(__xludf.DUMMYFUNCTION("""COMPUTED_VALUE"""),"Javier Muñoz Valenzuela") -> Javier Muñoz Valenzuela | D24: =IFERROR(__xludf.DUMMYFUNCTION("""COMPUTED_VALUE"""),"jav.muñoz@gmail.com") -> jav.muñoz@gmail.com | E24: =IFERROR(__xludf.DUMMYFUNCTION("""COMPUTED_VALUE"""),"Providencia") -> Providencia | F24: =IFERROR(__xludf.DUMMYFUNCTION("""COMPUTED_VALUE"""),"Santiago") -> Santiago | G24: =IFERROR(__xludf.DUMMYFUNCTION("""COMPUTED_VALUE"""),"Región Metropolitana") -> Región Metropolitana | H24: =IFERROR(__xludf.DUMMYFUNCTION("""COMPUTED_VALUE"""),2.014E7) -> 20140000
A25: =IFERROR(__xludf.DUMMYFUNCTION("""COMPUTED_VALUE"""),"CLI-0856") -> CLI-0856 | B25: =IFERROR(__xludf.DUMMYFUNCTION("""COMPUTED_VALUE"""),"15.379.306-8") -> 15.379.306-8 | C25: =IFERROR(__xludf.DUMMYFUNCTION("""COMPUTED_VALUE"""),"Gabriel Espinoza Vergara") -> Gabriel Espinoza Vergara | D25: =IFERROR(__xludf.DUMMYFUNCTION("""COMPUTED_VALUE"""),"gab.espinoza@empresa.cl") -> gab.espinoza@empresa.cl | E25: =IFERROR(__xludf.DUMMYFUNCTION("""COMPUTED_VALUE"""),"Santiago Centro") -> Santiago Centro | F25: =IFERROR(__xludf.DUMMYFUNCTION("""COMPUTED_VALUE"""),"Santiago") -> Santiago | G25: =IFERROR(__xludf.DUMMYFUNCTION("""COMPUTED_VALUE"""),"Región Metropolitana") -> Región Metropolitana | H25: =IFERROR(__xludf.DUMMYFUNCTION("""COMPUTED_VALUE"""),2.008E7) -> 20080000
A26: =IFERROR(__xludf.DUMMYFUNCTION("""COMPUTED_VALUE"""),"CLI-0322") -> CLI-0322 | B26: =IFERROR(__xludf.DUMMYFUNCTION("""COMPUTED_VALUE"""),"16.723.002-0") -> 16.723.002-0 | C26: =IFERROR(__xludf.DUMMYFUNCTION("""COMPUTED_VALUE"""),"Tomas Tapia Vergara") -> Tomas Tapia Vergara | D26: =IFERROR(__xludf.DUMMYFUNCTION("""COMPUTED_VALUE"""),"tom.tapia@consultora.cl") -> tom.tapia@consultora.cl | E26: =IFERROR(__xludf.DUMMYFUNCTION("""COMPUTED_VALUE"""),"Las Condes") -> Las Condes | F26: =IFERROR(__xludf.DUMMYFUNCTION("""COMPUTED_VALUE"""),"Santiago") -> Santiago | G26: =IFERROR(__xludf.DUMMYFUNCTION("""COMPUTED_VALUE"""),"Región Metropolitana") -> Región Metropolitana | H26: =IFERROR(__xludf.DUMMYFUNCTION("""COMPUTED_VALUE"""),2.003E7) -> 20030000
A27: =IFERROR(__xludf.DUMMYFUNCTION("""COMPUTED_VALUE"""),"CLI-0595") -> CLI-0595 | B27: =IFERROR(__xludf.DUMMYFUNCTION("""COMPUTED_VALUE"""),"14.504.587-8") -> 14.504.587-8 | C27: =IFERROR(__xludf.DUMMYFUNCTION("""COMPUTED_VALUE"""),"Carolina Soto Espinoza") -> Carolina Soto Espinoza | D27: =IFERROR(__xludf.DUMMYFUNCTION("""COMPUTED_VALUE"""),"car.soto@empresa.cl") -> car.soto@empresa.cl | E27: =IFERROR(__xludf.DUMMYFUNCTION("""COMPUTED_VALUE"""),"Maipú") -> Maipú | F27: =IFERROR(__xludf.DUMMYFUNCTION("""COMPUTED_VALUE"""),"Santiago") -> Santiago | G27: =IFERROR(__xludf.DUMMYFUNCTION("""COMPUTED_VALUE"""),"Región Metropolitana") -> Región Metropolitana | H27: =IFERROR(__xludf.DUMMYFUNCTION("""COMPUTED_VALUE"""),1.997E7) -> 19970000
A28: =IFERROR(__xludf.DUMMYFUNCTION("""COMPUTED_VALUE"""),"CLI-0773") -> CLI-0773 | B28: =IFERROR(__xludf.DUMMYFUNCTION("""COMPUTED_VALUE"""),"14361797-0") -> 14361797-0 | C28: =IFERROR(__xludf.DUMMYFUNCTION("""COMPUTED_VALUE"""),"Sofia Rodríguez Tapia") -> Sofia Rodríguez Tapia | D28: =IFERROR(__xludf.DUMMYFUNCTION("""COMPUTED_VALUE"""),"sof.rodríguez@sura.cl") -> sof.rodríguez@sura.cl | E28: =IFERROR(__xludf.DUMMYFUNCTION("""COMPUTED_VALUE"""),"Las Condes") -> Las Condes | F28: =IFERROR(__xludf.DUMMYFUNCTION("""COMPUTED_VALUE"""),"Santiago") -> Santiago | G28: =IFERROR(__xludf.DUMMYFUNCTION("""COMPUTED_VALUE"""),"Región Metropolitana") -> Región Metropolitana | H28: =IFERROR(__xludf.DUMMYFUNCTION("""COMPUTED_VALUE"""),1.996E7) -> 19960000
A29: =IFERROR(__xludf.DUMMYFUNCTION("""COMPUTED_VALUE"""),"CLI-0824") -> CLI-0824 | B29: =IFERROR(__xludf.DUMMYFUNCTION("""COMPUTED_VALUE"""),"19.801.145-6") -> 19.801.145-6 | C29: =IFERROR(__xludf.DUMMYFUNCTION("""COMPUTED_VALUE"""),"Claudio Soto González") -> Claudio Soto González | D29: =IFERROR(__xludf.DUMMYFUNCTION("""COMPUTED_VALUE"""),"cla.soto@outlook.cl") -> cla.soto@outlook.cl | E29: =IFERROR(__xludf.DUMMYFUNCTION("""COMPUTED_VALUE"""),"Las Condes") -> Las Condes | F29: =IFERROR(__xludf.DUMMYFUNCTION("""COMPUTED_VALUE"""),"Santiago") -> Santiago | G29: =IFERROR(__xludf.DUMMYFUNCTION("""COMPUTED_VALUE"""),"Región Metropolitana") -> Región Metropolitana | H29: =IFERROR(__xludf.DUMMYFUNCTION("""COMPUTED_VALUE"""),1.992E7) -> 19920000
A30: =IFERROR(__xludf.DUMMYFUNCTION("""COMPUTED_VALUE"""),"CLI-0898") -> CLI-0898 | B30: =IFERROR(__xludf.DUMMYFUNCTION("""COMPUTED_VALUE"""),"19.859.067-1") -> 19.859.067-1 | C30: =IFERROR(__xludf.DUMMYFUNCTION("""COMPUTED_VALUE"""),"Hernán Soto Pérez") -> Hernán Soto Pérez | D30: =IFERROR(__xludf.DUMMYFUNCTION("""COMPUTED_VALUE"""),"her.soto@sura.cl") -> her.soto@sura.cl | E30: =IFERROR(__xludf.DUMMYFUNCTION("""COMPUTED_VALUE"""),"Santiago Centro") -> Santiago Centro | F30: =IFERROR(__xludf.DUMMYFUNCTION("""COMPUTED_VALUE"""),"Santiago") -> Santiago | G30: =IFERROR(__xludf.DUMMYFUNCTION("""COMPUTED_VALUE"""),"Región Metropolitana") -> Región Metropolitana | H30: =IFERROR(__xludf.DUMMYFUNCTION("""COMPUTED_VALUE"""),1.992E7) -> 19920000
A31: =IFERROR(__xludf.DUMMYFUNCTION("""COMPUTED_VALUE"""),"CLI-0165") -> CLI-0165 | B31: =IFERROR(__xludf.DUMMYFUNCTION("""COMPUTED_VALUE"""),"22.022.194-3") -> 22.022.194-3 | C31: =IFERROR(__xludf.DUMMYFUNCTION("""COMPUTED_VALUE"""),"Paula Valenzuela Espinoza") -> Paula Valenzuela Espinoza | D31: =IFERROR(__xludf.DUMMYFUNCTION("""COMPUTED_VALUE"""),"pau.valenzuela@consultora.cl") -> pau.valenzuela@consultora.cl | E31: =IFERROR(__xludf.DUMMYFUNCTION("""COMPUTED_VALUE"""),"Santiago Centro") -> Santiago Centro | F31: =IFERROR(__xludf.DUMMYFUNCTION("""COMPUTED_VALUE"""),"Santiago") -> Santiago | G31: =IFERROR(__xludf.DUMMYFUNCTION("""COMPUTED_VALUE"""),"Región Metropolitana") -> Región Metropolitana | H31: =IFERROR(__xludf.DUMMYFUNCTION("""COMPUTED_VALUE"""),1.988E7) -> 19880000
A32: =IFERROR(__xludf.DUMMYFUNCTION("""COMPUTED_VALUE"""),"CLI-0559") -> CLI-0559 | B32: =IFERROR(__xludf.DUMMYFUNCTION("""COMPUTED_VALUE"""),"16.570.174-3") -> 16.570.174-3 | C32: =IFERROR(__xludf.DUMMYFUNCTION("""COMPUTED_VALUE"""),"Catalina Araya Morales") -> Catalina Araya Morales | D32: =IFERROR(__xludf.DUMMYFUNCTION("""COMPUTED_VALUE"""),"cat.araya@sura.cl") -> cat.araya@sura.cl | E32: =IFERROR(__xludf.DUMMYFUNCTION("""COMPUTED_VALUE"""),"Santiago Centro") -> Santiago Centro | F32: =IFERROR(__xludf.DUMMYFUNCTION("""COMPUTED_VALUE"""),"Santiago") -> Santiago | G32: =IFERROR(__xludf.DUMMYFUNCTION("""COMPUTED_VALUE"""),"Región Metropolitana") -> Región Metropolitana | H32: =IFERROR(__xludf.DUMMYFUNCTION("""COMPUTED_VALUE"""),1.976E7) -> 19760000
A33: =IFERROR(__xludf.DUMMYFUNCTION("""COMPUTED_VALUE"""),"CLI-0755") -> CLI-0755 | B33: =IFERROR(__xludf.DUMMYFUNCTION("""COMPUTED_VALUE"""),"20.274.430-9") -> 20.274.430-9 | C33: =IFERROR(__xludf.DUMMYFUNCTION("""COMPUTED_VALUE"""),"Francisca Díaz González") -> Francisca Díaz González | D33: =IFERROR(__xludf.DUMMYFUNCTION("""COMPUTED_VALUE"""),"fra.díaz@outlook.cl") -> fra.díaz@outlook.cl | E33: =IFERROR(__xludf.DUMMYFUNCTION("""COMPUTED_VALUE"""),"Santiago Centro") -> Santiago Centro | F33: =IFERROR(__xludf.DUMMYFUNCTION("""COMPUTED_VALUE"""),"Santiago") -> Santiago | G33: =IFERROR(__xludf.DUMMYFUNCTION("""COMPUTED_VALUE"""),"Región Metropolitana") -> Región Metropolitana | H33: =IFERROR(__xludf.DUMMYFUNCTION("""COMPUTED_VALUE"""),1.976E7) -> 19760000
A34: =IFERROR(__xludf.DUMMYFUNCTION("""COMPUTED_VALUE"""),"CLI-0363") -> CLI-0363 | B34: =IFERROR(__xludf.DUMMYFUNCTION("""COMPUTED_VALUE"""),"18770320-1") -> 18770320-1 | C34: =IFERROR(__xludf.DUMMYFUNCTION("""COMPUTED_VALUE"""),"Javiera Soto Silva") -> Javiera Soto Silva | D34: =IFERROR(__xludf.DUMMYFUNCTION("""COMPUTED_VALUE"""),"jav.soto@sura.cl") -> jav.soto@sura.cl | E34: =IFERROR(__xludf.DUMMYFUNCTION("""COMPUTED_VALUE"""),"Santiago Centro") -> Santiago Centro | F34: =IFERROR(__xludf.DUMMYFUNCTION("""COMPUTED_VALUE"""),"Santiago") -> Santiago | G34: =IFERROR(__xludf.DUMMYFUNCTION("""COMPUTED_VALUE"""),"Región Metropolitana") -> Región Metropolitana | H34: =IFERROR(__xludf.DUMMYFUNCTION("""COMPUTED_VALUE"""),1.975E7) -> 19750000
A35: =IFERROR(__xludf.DUMMYFUNCTION("""COMPUTED_VALUE"""),"CLI-0186") -> CLI-0186 | B35: =IFERROR(__xludf.DUMMYFUNCTION("""COMPUTED_VALUE"""),"15.480.982-0") -> 15.480.982-0 | C35: =IFERROR(__xludf.DUMMYFUNCTION("""COMPUTED_VALUE"""),"Diego Araya López") -> Diego Araya López | D35: =IFERROR(__xludf.DUMMYFUNCTION("""COMPUTED_VALUE"""),"die.araya@empresa.cl") -> die.araya@empresa.cl | E35: =IFERROR(__xludf.DUMMYFUNCTION("""COMPUTED_VALUE"""),"Las Condes") -> Las Condes | F35: =IFERROR(__xludf.DUMMYFUNCTION("""COMPUTED_VALUE"""),"Santiago") -> Santiago | G35: =IFERROR(__xludf.DUMMYFUNCTION("""COMPUTED_VALUE"""),"Región Metropolitana") -> Región Metropolitana | H35: =IFERROR(__xludf.DUMMYFUNCTION("""COMPUTED_VALUE"""),1.971E7) -> 19710000
A36: =IFERROR(__xludf.DUMMYFUNCTION("""COMPUTED_VALUE"""),"CLI-0711") -> CLI-0711 | B36: =IFERROR(__xludf.DUMMYFUNCTION("""COMPUTED_VALUE"""),"13.292.673-5") -> 13.292.673-5 | C36: =IFERROR(__xludf.DUMMYFUNCTION("""COMPUTED_VALUE"""),"Javiera Soto López") -> Javiera Soto López | D36: =IFERROR(__xludf.DUMMYFUNCTION("""COMPUTED_VALUE"""),"jav.soto@servicios.cl") -> jav.soto@servicios.cl | E36: =IFERROR(__xludf.DUMMYFUNCTION("""COMPUTED_VALUE"""),"Las Condes") -> Las Condes | F36: =IFERROR(__xludf.DUMMYFUNCTION("""COMPUTED_VALUE"""),"Santiago") -> Santiago | G36: =IFERROR(__xludf.DUMMYFUNCTION("""COMPUTED_VALUE"""),"Región Metropolitana") -> Región Metropolitana | H36: =IFERROR(__xludf.DUMMYFUNCTION("""COMPUTED_VALUE"""),1.969E7) -> 19690000
A37: =IFERROR(__xludf.DUMMYFUNCTION("""COMPUTED_VALUE"""),"CLI-0144") -> CLI-0144 | B37: =IFERROR(__xludf.DUMMYFUNCTION("""COMPUTED_VALUE"""),"19540155-7") -> 19540155-7 | C37: =IFERROR(__xludf.DUMMYFUNCTION("""COMPUTED_VALUE"""),"Ignacio Soto Vergara") -> Ignacio Soto Vergara | D37: =IFERROR(__xludf.DUMMYFUNCTION("""COMPUTED_VALUE"""),"ign.soto@sura.cl") -> ign.soto@sura.cl | E37: =IFERROR(__xludf.DUMMYFUNCTION("""COMPUTED_VALUE"""),"Providencia") -> Providencia | F37: =IFERROR(__xludf.DUMMYFUNCTION("""COMPUTED_VALUE"""),"Santiago") -> Santiago | G37: =IFERROR(__xludf.DUMMYFUNCTION("""COMPUTED_VALUE"""),"Región Metropolitana") -> Región Metropolitana | H37: =IFERROR(__xludf.DUMMYFUNCTION("""COMPUTED_VALUE"""),1.952E7) -> 19520000
A38: =IFERROR(__xludf.DUMMYFUNCTION("""COMPUTED_VALUE"""),"CLI-0125") -> CLI-0125 | B38: =IFERROR(__xludf.DUMMYFUNCTION("""COMPUTED_VALUE"""),"14.294.333-2") -> 14.294.333-2 | C38: =IFERROR(__xludf.DUMMYFUNCTION("""COMPUTED_VALUE"""),"Javiera Muñoz Rojas") -> Javiera Muñoz Rojas | D38: =IFERROR(__xludf.DUMMYFUNCTION("""COMPUTED_VALUE"""),"jav.muñoz@outlook.cl") -> jav.muñoz@outlook.cl | E38: =IFERROR(__xludf.DUMMYFUNCTION("""COMPUTED_VALUE"""),"Maipú") -> Maipú | F38: =IFERROR(__xludf.DUMMYFUNCTION("""COMPUTED_VALUE"""),"Santiago") -> Santiago | G38: =IFERROR(__xludf.DUMMYFUNCTION("""COMPUTED_VALUE"""),"Región Metropolitana") -> Región Metropolitana | H38: =IFERROR(__xludf.DUMMYFUNCTION("""COMPUTED_VALUE"""),1.95E7) -> 19500000
A39: =IFERROR(__xludf.DUMMYFUNCTION("""COMPUTED_VALUE"""),"CLI-0290") -> CLI-0290 | B39: =IFERROR(__xludf.DUMMYFUNCTION("""COMPUTED_VALUE"""),"13391356-5") -> 13391356-5 | C39: =IFERROR(__xludf.DUMMYFUNCTION("""COMPUTED_VALUE"""),"Esteban Araya Pérez") -> Esteban Araya Pérez | D39: =IFERROR(__xludf.DUMMYFUNCTION("""COMPUTED_VALUE"""),"est.araya@outlook.cl") -> est.araya@outlook.cl | E39: =IFERROR(__xludf.DUMMYFUNCTION("""COMPUTED_VALUE"""),"Santiago Centro") -> Santiago Centro | F39: =IFERROR(__xludf.DUMMYFUNCTION("""COMPUTED_VALUE"""),"Santiago") -> Santiago | G39: =IFERROR(__xludf.DUMMYFUNCTION("""COMPUTED_VALUE"""),"Región Metropolitana") -> Región Metropolitana | H39: =IFERROR(__xludf.DUMMYFUNCTION("""COMPUTED_VALUE"""),1.941E7) -> 19410000
A40: =IFERROR(__xludf.DUMMYFUNCTION("""COMPUTED_VALUE"""),"CLI-0176") -> CLI-0176 | B40: =IFERROR(__xludf.DUMMYFUNCTION("""COMPUTED_VALUE"""),"16174998-K") -> 16174998-K | C40: =IFERROR(__xludf.DUMMYFUNCTION("""COMPUTED_VALUE"""),"Felipe Rodríguez Silva") -> Felipe Rodríguez Silva | D40: =IFERROR(__xludf.DUMMYFUNCTION("""COMPUTED_VALUE"""),"fel.rodríguez@outlook.cl") -> fel.rodríguez@outlook.cl | E40: =IFERROR(__xludf.DUMMYFUNCTION("""COMPUTED_VALUE"""),"Providencia") -> Providencia | F40: =IFERROR(__xludf.DUMMYFUNCTION("""COMPUTED_VALUE"""),"Santiago") -> Santiago | G40: =IFERROR(__xludf.DUMMYFUNCTION("""COMPUTED_VALUE"""),"Región Metropolitana") -> Región Metropolitana | H40: =IFERROR(__xludf.DUMMYFUNCTION("""COMPUTED_VALUE"""),1.941E7) -> 19410000
A41: =IFERROR(__xludf.DUMMYFUNCTION("""COMPUTED_VALUE"""),"CLI-0441") -> CLI-0441 | B41: =IFERROR(__xludf.DUMMYFUNCTION("""COMPUTED_VALUE"""),"16.987.090-9") -> 16.987.090-9 | C41: =IFERROR(__xludf.DUMMYFUNCTION("""COMPUTED_VALUE"""),"Macarena Soto Muñoz") -> Macarena Soto Muñoz | D41: =IFERROR(__xludf.DUMMYFUNCTION("""COMPUTED_VALUE"""),"mac.soto@outlook.cl") -> mac.soto@outlook.cl | E41: =IFERROR(__xludf.DUMMYFUNCTION("""COMPUTED_VALUE"""),"Las Condes") -> Las Condes | F41: =IFERROR(__xludf.DUMMYFUNCTION("""COMPUTED_VALUE"""),"Santiago") -> Santiago | G41: =IFERROR(__xludf.DUMMYFUNCTION("""COMPUTED_VALUE"""),"Región Metropolitana") -> Región Metropolitana | H41: =IFERROR(__xludf.DUMMYFUNCTION("""COMPUTED_VALUE"""),1.935E7) -> 19350000
A42: =IFERROR(__xludf.DUMMYFUNCTION("""COMPUTED_VALUE"""),"CLI-0174") -> CLI-0174 | B42: =IFERROR(__xludf.DUMMYFUNCTION("""COMPUTED_VALUE"""),"18.284.772-7") -> 18.284.772-7 | C42: =IFERROR(__xludf.DUMMYFUNCTION("""COMPUTED_VALUE"""),"Hernán Morales Contreras") -> Hernán Morales Contreras | D42: =IFERROR(__xludf.DUMMYFUNCTION("""COMPUTED_VALUE"""),"her.morales@empresa.cl") -> her.morales@empresa.cl | E42: =IFERROR(__xludf.DUMMYFUNCTION("""COMPUTED_VALUE"""),"Maipú") -> Maipú | F42: =IFERROR(__xludf.DUMMYFUNCTION("""COMPUTED_VALUE"""),"Santiago") -> Santiago | G42: =IFERROR(__xludf.DUMMYFUNCTION("""COMPUTED_VALUE"""),"Región Metropolitana") -> Región Metropolitana | H42: =IFERROR(__xludf.DUMMYFUNCTION("""COMPUTED_VALUE"""),1.933E7) -> 19330000
A43: =IFERROR(__xludf.DUMMYFUNCTION("""COMPUTED_VALUE"""),"CLI-0374") -> CLI-0374 | B43: =IFERROR(__xludf.DUMMYFUNCTION("""COMPUTED_VALUE"""),"18.441.773-K") -> 18.441.773-K | C43: =IFERROR(__xludf.DUMMYFUNCTION("""COMPUTED_VALUE"""),"Cristián Valenzuela Valenzuela") -> Cristián Valenzuela Valenzuela | D43: =IFERROR(__xludf.DUMMYFUNCTION("""COMPUTED_VALUE"""),"cri.valenzuela@gmail.com") -> cri.valenzuela@gmail.com | E43: =IFERROR(__xludf.DUMMYFUNCTION("""COMPUTED_VALUE"""),"Providencia") -> Providencia | F43: =IFERROR(__xludf.DUMMYFUNCTION("""COMPUTED_VALUE"""),"Santiago") -> Santiago | G43: =IFERROR(__xludf.DUMMYFUNCTION("""COMPUTED_VALUE"""),"Región Metropolitana") -> Región Metropolitana | H43: =IFERROR(__xludf.DUMMYFUNCTION("""COMPUTED_VALUE"""),1.923E7) -> 19230000
A44: =IFERROR(__xludf.DUMMYFUNCTION("""COMPUTED_VALUE"""),"CLI-0285") -> CLI-0285 | B44: =IFERROR(__xludf.DUMMYFUNCTION("""COMPUTED_VALUE"""),"12.564.358-1") -> 12.564.358-1 | C44: =IFERROR(__xludf.DUMMYFUNCTION("""COMPUTED_VALUE"""),"Javiera Silva Araya") -> Javiera Silva Araya | D44: =IFERROR(__xludf.DUMMYFUNCTION("""COMPUTED_VALUE"""),"jav.silva@gmail.com") -> jav.silva@gmail.com | E44: =IFERROR(__xludf.DUMMYFUNCTION("""COMPUTED_VALUE"""),"Providencia") -> Providencia | F44: =IFERROR(__xludf.DUMMYFUNCTION("""COMPUTED_VALUE"""),"Santiago") -> Santiago | G44: =IFERROR(__xludf.DUMMYFUNCTION("""COMPUTED_VALUE"""),"Región Metropolitana") -> Región Metropolitana | H44: =IFERROR(__xludf.DUMMYFUNCTION("""COMPUTED_VALUE"""),1.92E7) -> 19200000
A45: =IFERROR(__xludf.DUMMYFUNCTION("""COMPUTED_VALUE"""),"CLI-0561") -> CLI-0561 | B45: =IFERROR(__xludf.DUMMYFUNCTION("""COMPUTED_VALUE"""),"14.622.252-K") -> 14.622.252-K | C45: =IFERROR(__xludf.DUMMYFUNCTION("""COMPUTED_VALUE"""),"Daniela Sepúlveda Morales") -> Daniela Sepúlveda Morales | D45: =IFERROR(__xludf.DUMMYFUNCTION("""COMPUTED_VALUE"""),"dan.sepúlveda@outlook.cl") -> dan.sepúlveda@outlook.cl | E45: =IFERROR(__xludf.DUMMYFUNCTION("""COMPUTED_VALUE"""),"Santiago Centro") -> Santiago Centro | F45: =IFERROR(__xludf.DUMMYFUNCTION("""COMPUTED_VALUE"""),"Santiago") -> Santiago | G45: =IFERROR(__xludf.DUMMYFUNCTION("""COMPUTED_VALUE"""),"Región Metropolitana") -> Región Metropolitana | H45: =IFERROR(__xludf.DUMMYFUNCTION("""COMPUTED_VALUE"""),1.911E7) -> 19110000
A46: =IFERROR(__xludf.DUMMYFUNCTION("""COMPUTED_VALUE"""),"CLI-0582") -> CLI-0582 | B46: =IFERROR(__xludf.DUMMYFUNCTION("""COMPUTED_VALUE"""),"19499949-6") -> 19499949-6 | C46: =IFERROR(__xludf.DUMMYFUNCTION("""COMPUTED_VALUE"""),"Diego Rojas Araya") -> Diego Rojas Araya | D46: =IFERROR(__xludf.DUMMYFUNCTION("""COMPUTED_VALUE"""),"die.rojas@outlook.cl") -> die.rojas@outlook.cl | E46: =IFERROR(__xludf.DUMMYFUNCTION("""COMPUTED_VALUE"""),"Ñuñoa") -> Ñuñoa | F46: =IFERROR(__xludf.DUMMYFUNCTION("""COMPUTED_VALUE"""),"Santiago") -> Santiago | G46: =IFERROR(__xludf.DUMMYFUNCTION("""COMPUTED_VALUE"""),"Región Metropolitana") -> Región Metropolitana | H46: =IFERROR(__xludf.DUMMYFUNCTION("""COMPUTED_VALUE"""),1.909E7) -> 19090000
A47: =IFERROR(__xludf.DUMMYFUNCTION("""COMPUTED_VALUE"""),"CLI-0945") -> CLI-0945 | B47: =IFERROR(__xludf.DUMMYFUNCTION("""COMPUTED_VALUE"""),"14.307.016-8") -> 14.307.016-8 | C47: =IFERROR(__xludf.DUMMYFUNCTION("""COMPUTED_VALUE"""),"Francisca López Sepúlveda") -> Francisca López Sepúlveda | D47: =IFERROR(__xludf.DUMMYFUNCTION("""COMPUTED_VALUE"""),"fra.lópez@gmail.com") -> fra.lópez@gmail.com | E47: =IFERROR(__xludf.DUMMYFUNCTION("""COMPUTED_VALUE"""),"Ñuñoa") -> Ñuñoa | F47: =IFERROR(__xludf.DUMMYFUNCTION("""COMPUTED_VALUE"""),"Santiago") -> Santiago | G47: =IFERROR(__xludf.DUMMYFUNCTION("""COMPUTED_VALUE"""),"Región Metropolitana") -> Región Metropolitana | H47: =IFERROR(__xludf.DUMMYFUNCTION("""COMPUTED_VALUE"""),1.901E7) -> 19010000
A48: =IFERROR(__xludf.DUMMYFUNCTION("""COMPUTED_VALUE"""),"CLI-0906") -> CLI-0906 | B48: =IFERROR(__xludf.DUMMYFUNCTION("""COMPUTED_VALUE"""),"11.106.386-8") -> 11.106.386-8 | C48: =IFERROR(__xludf.DUMMYFUNCTION("""COMPUTED_VALUE"""),"Diego Pérez Rodríguez") -> Diego Pérez Rodríguez | D48: =IFERROR(__xludf.DUMMYFUNCTION("""COMPUTED_VALUE"""),"die.pérez@outlook.cl") -> die.pérez@outlook.cl | E48: =IFERROR(__xludf.DUMMYFUNCTION("""COMPUTED_VALUE"""),"Providencia") -> Providencia | F48: =IFERROR(__xludf.DUMMYFUNCTION("""COMPUTED_VALUE"""),"Santiago") -> Santiago | G48: =IFERROR(__xludf.DUMMYFUNCTION("""COMPUTED_VALUE"""),"Región Metropolitana") -> Región Metropolitana | H48: =IFERROR(__xludf.DUMMYFUNCTION("""COMPUTED_VALUE"""),1.893E7) -> 18930000
A49: =IFERROR(__xludf.DUMMYFUNCTION("""COMPUTED_VALUE"""),"CLI-0417") -> CLI-0417 | B49: =IFERROR(__xludf.DUMMYFUNCTION("""COMPUTED_VALUE"""),"20.174.207-2") -> 20.174.207-2 | C49: =IFERROR(__xludf.DUMMYFUNCTION("""COMPUTED_VALUE"""),"Fernanda Morales González") -> Fernanda Morales González | D49: =IFERROR(__xludf.DUMMYFUNCTION("""COMPUTED_VALUE"""),"fer.morales@consultora.cl") -> fer.morales@consultora.cl | E49: =IFERROR(__xludf.DUMMYFUNCTION("""COMPUTED_VALUE"""),"Maipú") -> Maipú | F49: =IFERROR(__xludf.DUMMYFUNCTION("""COMPUTED_VALUE"""),"Santiago") -> Santiago | G49: =IFERROR(__xludf.DUMMYFUNCTION("""COMPUTED_VALUE"""),"Región Metropolitana") -> Región Metropolitana | H49: =IFERROR(__xludf.DUMMYFUNCTION("""COMPUTED_VALUE"""),1.89E7) -> 18900000
A50: =IFERROR(__xludf.DUMMYFUNCTION("""COMPUTED_VALUE"""),"CLI-0514") -> CLI-0514 | B50: =IFERROR(__xludf.DUMMYFUNCTION("""COMPUTED_VALUE"""),"19.362.264-8") -> 19.362.264-8 | C50: =IFERROR(__xludf.DUMMYFUNCTION("""COMPUTED_VALUE"""),"Matías Rojas Rodríguez") -> Matías Rojas Rodríguez | D50: =IFERROR(__xludf.DUMMYFUNCTION("""COMPUTED_VALUE"""),"mat.rojas@empresa.cl") -> mat.rojas@empresa.cl | E50: =IFERROR(__xludf.DUMMYFUNCTION("""COMPUTED_VALUE"""),"Providencia") -> Providencia | F50: =IFERROR(__xludf.DUMMYFUNCTION("""COMPUTED_VALUE"""),"Santiago") -> Santiago | G50: =IFERROR(__xludf.DUMMYFUNCTION("""COMPUTED_VALUE"""),"Región Metropolitana") -> Región Metropolitana | H50: =IFERROR(__xludf.DUMMYFUNCTION("""COMPUTED_VALUE"""),1.887E7) -> 18870000
A51: =IFERROR(__xludf.DUMMYFUNCTION("""COMPUTED_VALUE"""),"CLI-0784") -> CLI-0784 | B51: =IFERROR(__xludf.DUMMYFUNCTION("""COMPUTED_VALUE"""),"17.956.679-5") -> 17.956.679-5 | C51: =IFERROR(__xludf.DUMMYFUNCTION("""COMPUTED_VALUE"""),"Tomas Rodríguez Valenzuela") -> Tomas Rodríguez Valenzuela | D51: =IFERROR(__xludf.DUMMYFUNCTION("""COMPUTED_VALUE"""),"tom.rodríguez@gmail.com") -> tom.rodríguez@gmail.com | E51: =IFERROR(__xludf.DUMMYFUNCTION("""COMPUTED_VALUE"""),"Santiago Centro") -> Santiago Centro | F51: =IFERROR(__xludf.DUMMYFUNCTION("""COMPUTED_VALUE"""),"Santiago") -> Santiago | G51: =IFERROR(__xludf.DUMMYFUNCTION("""COMPUTED_VALUE"""),"Región Metropolitana") -> Región Metropolitana | H51: =IFERROR(__xludf.DUMMYFUNCTION("""COMPUTED_VALUE"""),1.879E7) -> 18790000
A52: =IFERROR(__xludf.DUMMYFUNCTION("""COMPUTED_VALUE"""),"CLI-0683") -> CLI-0683 | B52: =IFERROR(__xludf.DUMMYFUNCTION("""COMPUTED_VALUE"""),"17.993.339-9") -> 17.993.339-9 | C52: =IFERROR(__xludf.DUMMYFUNCTION("""COMPUTED_VALUE"""),"Francisca Silva Contreras") -> Francisca Silva Contreras | D52: =IFERROR(__xludf.DUMMYFUNCTION("""COMPUTED_VALUE"""),"fra.silva@sura.cl") -> fra.silva@sura.cl | E52: =IFERROR(__xludf.DUMMYFUNCTION("""COMPUTED_VALUE"""),"Maipú") -> Maipú | F52: =IFERROR(__xludf.DUMMYFUNCTION("""COMPUTED_VALUE"""),"Santiago") -> Santiago | G52: =IFERROR(__xludf.DUMMYFUNCTION("""COMPUTED_VALUE"""),"Región Metropolitana") -> Región Metropolitana | H52: =IFERROR(__xludf.DUMMYFUNCTION("""COMPUTED_VALUE"""),1.875E7) -> 18750000
A53: =IFERROR(__xludf.DUMMYFUNCTION("""COMPUTED_VALUE"""),"CLI-0951") -> CLI-0951 | B53: =IFERROR(__xludf.DUMMYFUNCTION("""COMPUTED_VALUE"""),"16.895.044-K") -> 16.895.044-K | C53: =IFERROR(__xludf.DUMMYFUNCTION("""COMPUTED_VALUE"""),"Valentina Fuentes Contreras") -> Valentina Fuentes Contreras | D53: =IFERROR(__xludf.DUMMYFUNCTION("""COMPUTED_VALUE"""),"val.fuentes@empresa.cl") -> val.fuentes@empresa.cl | E53: =IFERROR(__xludf.DUMMYFUNCTION("""COMPUTED_VALUE"""),"Santiago Centro") -> Santiago Centro | F53: =IFERROR(__xludf.DUMMYFUNCTION("""COMPUTED_VALUE"""),"Santiago") -> Santiago | G53: =IFERROR(__xludf.DUMMYFUNCTION("""COMPUTED_VALUE"""),"Región Metropolitana") -> Región Metropolitana | H53: =IFERROR(__xludf.DUMMYFUNCTION("""COMPUTED_VALUE"""),1.874E7) -> 18740000
A54: =IFERROR(__xludf.DUMMYFUNCTION("""COMPUTED_VALUE"""),"CLI-0212") -> CLI-0212 | B54: =IFERROR(__xludf.DUMMYFUNCTION("""COMPUTED_VALUE"""),"18.622.686-3") -> 18.622.686-3 | C54: =IFERROR(__xludf.DUMMYFUNCTION("""COMPUTED_VALUE"""),"Claudio Rojas Valenzuela") -> Claudio Rojas Valenzuela | D54: =IFERROR(__xludf.DUMMYFUNCTION("""COMPUTED_VALUE"""),"cla.rojas@gmail.com") -> cla.rojas@gmail.com | E54: =IFERROR(__xludf.DUMMYFUNCTION("""COMPUTED_VALUE"""),"Maipú") -> Maipú | F54: =IFERROR(__xludf.DUMMYFUNCTION("""COMPUTED_VALUE"""),"Santiago") -> Santiago | G54: =IFERROR(__xludf.DUMMYFUNCTION("""COMPUTED_VALUE"""),"Región Metropolitana") -> Región Metropolitana | H54: =IFERROR(__xludf.DUMMYFUNCTION("""COMPUTED_VALUE"""),1.873E7) -> 18730000
A55: =IFERROR(__xludf.DUMMYFUNCTION("""COMPUTED_VALUE"""),"CLI-0467") -> CLI-0467 | B55: =IFERROR(__xludf.DUMMYFUNCTION("""COMPUTED_VALUE"""),"14.863.931-1") -> 14.863.931-1 | C55: =IFERROR(__xludf.DUMMYFUNCTION("""COMPUTED_VALUE"""),"Valentina Muñoz Díaz") -> Valentina Muñoz Díaz | D55: =IFERROR(__xludf.DUMMYFUNCTION("""COMPUTED_VALUE"""),"val.muñoz@sura.cl") -> val.muñoz@sura.cl | E55: =IFERROR(__xludf.DUMMYFUNCTION("""COMPUTED_VALUE"""),"Santiago Centro") -> Santiago Centro | F55: =IFERROR(__xludf.DUMMYFUNCTION("""COMPUTED_VALUE"""),"Santiago") -> Santiago | G55: =IFERROR(__xludf.DUMMYFUNCTION("""COMPUTED_VALUE"""),"Región Metropolitana") -> Región Metropolitana | H55: =IFERROR(__xludf.DUMMYFUNCTION("""COMPUTED_VALUE"""),1.873E7) -> 18730000
A56: =IFERROR(__xludf.DUMMYFUNCTION("""COMPUTED_VALUE"""),"CLI-0388") -> CLI-0388 | B56: =IFERROR(__xludf.DUMMYFUNCTION("""COMPUTED_VALUE"""),"21.035.069-7") -> 21.035.069-7 | C56: =IFERROR(__xludf.DUMMYFUNCTION("""COMPUTED_VALUE"""),"Gabriel Muñoz Espinoza") -> Gabriel Muñoz Espinoza | D56: =IFERROR(__xludf.DUMMYFUNCTION("""COMPUTED_VALUE"""),"gab.muñoz@gmail.com") -> gab.muñoz@gmail.com | E56: =IFERROR(__xludf.DUMMYFUNCTION("""COMPUTED_VALUE"""),"Providencia") -> Providencia | F56: =IFERROR(__xludf.DUMMYFUNCTION("""COMPUTED_VALUE"""),"Santiago") -> Santiago | G56: =IFERROR(__xludf.DUMMYFUNCTION("""COMPUTED_VALUE"""),"Región Metropolitana") -> Región Metropolitana | H56: =IFERROR(__xludf.DUMMYFUNCTION("""COMPUTED_VALUE"""),1.865E7) -> 18650000
A57: =IFERROR(__xludf.DUMMYFUNCTION("""COMPUTED_VALUE"""),"CLI-0695") -> CLI-0695 | B57: =IFERROR(__xludf.DUMMYFUNCTION("""COMPUTED_VALUE"""),"22.064.179-3") -> 22.064.179-3 | C57: =IFERROR(__xludf.DUMMYFUNCTION("""COMPUTED_VALUE"""),"Sofia Rodríguez Vergara") -> Sofia Rodríguez Vergara | D57: =IFERROR(__xludf.DUMMYFUNCTION("""COMPUTED_VALUE"""),"sof.rodríguez@servicios.cl") -> sof.rodríguez@servicios.cl | E57: =IFERROR(__xludf.DUMMYFUNCTION("""COMPUTED_VALUE"""),"Las Condes") -> Las Condes | F57: =IFERROR(__xludf.DUMMYFUNCTION("""COMPUTED_VALUE"""),"Santiago") -> Santiago | G57: =IFERROR(__xludf.DUMMYFUNCTION("""COMPUTED_VALUE"""),"Región Metropolitana") -> Región Metropolitana | H57: =IFERROR(__xludf.DUMMYFUNCTION("""COMPUTED_VALUE"""),1.861E7) -> 18610000
A58: =IFERROR(__xludf.DUMMYFUNCTION("""COMPUTED_VALUE"""),"CLI-0379") -> CLI-0379 | B58: =IFERROR(__xludf.DUMMYFUNCTION("""COMPUTED_VALUE"""),"15.243.099-8") -> 15.243.099-8 | C58: =IFERROR(__xludf.DUMMYFUNCTION("""COMPUTED_VALUE"""),"Carolina Espinoza Díaz") -> Carolina Espinoza Díaz | D58: =IFERROR(__xludf.DUMMYFUNCTION("""COMPUTED_VALUE"""),"car.espinoza@consultora.cl") -> car.espinoza@consultora.cl | E58: =IFERROR(__xludf.DUMMYFUNCTION("""COMPUTED_VALUE"""),"Maipú") -> Maipú | F58: =IFERROR(__xludf.DUMMYFUNCTION("""COMPUTED_VALUE"""),"Santiago") -> Santiago | G58: =IFERROR(__xludf.DUMMYFUNCTION("""COMPUTED_VALUE"""),"Región Metropolitana") -> Región Metropolitana | H58: =IFERROR(__xludf.DUMMYFUNCTION("""COMPUTED_VALUE"""),1.859E7) -> 18590000
A59: =IFERROR(__xludf.DUMMYFUNCTION("""COMPUTED_VALUE"""),"CLI-0700") -> CLI-0700 | B59: =IFERROR(__xludf.DUMMYFUNCTION("""COMPUTED_VALUE"""),"19062672-8") -> 19062672-8 | C59: =IFERROR(__xludf.DUMMYFUNCTION("""COMPUTED_VALUE"""),"Mauricio González Silva") -> Mauricio González Silva | D59: =IFERROR(__xludf.DUMMYFUNCTION("""COMPUTED_VALUE"""),"mau.gonzález@outlook.cl") -> mau.gonzález@outlook.cl | E59: =IFERROR(__xludf.DUMMYFUNCTION("""COMPUTED_VALUE"""),"Maipú") -> Maipú | F59: =IFERROR(__xludf.DUMMYFUNCTION("""COMPUTED_VALUE"""),"Santiago") -> Santiago | G59: =IFERROR(__xludf.DUMMYFUNCTION("""COMPUTED_VALUE"""),"Región Metropolitana") -> Región Metropolitana | H59: =IFERROR(__xludf.DUMMYFUNCTION("""COMPUTED_VALUE"""),1.859E7) -> 18590000
A60: =IFERROR(__xludf.DUMMYFUNCTION("""COMPUTED_VALUE"""),"CLI-0676") -> CLI-0676 | B60: =IFERROR(__xludf.DUMMYFUNCTION("""COMPUTED_VALUE"""),"14186186-0") -> 14186186-0 | C60: =IFERROR(__xludf.DUMMYFUNCTION("""COMPUTED_VALUE"""),"Mauricio González López") -> Mauricio González López | D60: =IFERROR(__xludf.DUMMYFUNCTION("""COMPUTED_VALUE"""),"mau.gonzález@consultora.cl") -> mau.gonzález@consultora.cl | E60: =IFERROR(__xludf.DUMMYFUNCTION("""COMPUTED_VALUE"""),"Ñuñoa") -> Ñuñoa | F60: =IFERROR(__xludf.DUMMYFUNCTION("""COMPUTED_VALUE"""),"Santiago") -> Santiago | G60: =IFERROR(__xludf.DUMMYFUNCTION("""COMPUTED_VALUE"""),"Región Metropolitana") -> Región Metropolitana | H60: =IFERROR(__xludf.DUMMYFUNCTION("""COMPUTED_VALUE"""),1.843E7) -> 18430000
A61: =IFERROR(__xludf.DUMMYFUNCTION("""COMPUTED_VALUE"""),"CLI-0616") -> CLI-0616 | B61: =IFERROR(__xludf.DUMMYFUNCTION("""COMPUTED_VALUE"""),"12.785.688-8") -> 12.785.688-8 | C61: =IFERROR(__xludf.DUMMYFUNCTION("""COMPUTED_VALUE"""),"Claudio Tapia Morales") -> Claudio Tapia Morales | D61: =IFERROR(__xludf.DUMMYFUNCTION("""COMPUTED_VALUE"""),"cla.tapia@outlook.cl") -> cla.tapia@outlook.cl | E61: =IFERROR(__xludf.DUMMYFUNCTION("""COMPUTED_VALUE"""),"Santiago Centro") -> Santiago Centro | F61: =IFERROR(__xludf.DUMMYFUNCTION("""COMPUTED_VALUE"""),"Santiago") -> Santiago | G61: =IFERROR(__xludf.DUMMYFUNCTION("""COMPUTED_VALUE"""),"Región Metropolitana") -> Región Metropolitana | H61: =IFERROR(__xludf.DUMMYFUNCTION("""COMPUTED_VALUE"""),1.838E7) -> 18380000
A62: =IFERROR(__xludf.DUMMYFUNCTION("""COMPUTED_VALUE"""),"CLI-0053") -> CLI-0053 | B62: =IFERROR(__xludf.DUMMYFUNCTION("""COMPUTED_VALUE"""),"21.890.262-5") -> 21.890.262-5 | C62: =IFERROR(__xludf.DUMMYFUNCTION("""COMPUTED_VALUE"""),"Daniela Rodríguez Pérez") -> Daniela Rodríguez Pérez | D62: =IFERROR(__xludf.DUMMYFUNCTION("""COMPUTED_VALUE"""),"dan.rodríguez@empresa.cl") -> dan.rodríguez@empresa.cl | E62: =IFERROR(__xludf.DUMMYFUNCTION("""COMPUTED_VALUE"""),"Providencia") -> Providencia | F62: =IFERROR(__xludf.DUMMYFUNCTION("""COMPUTED_VALUE"""),"Santiago") -> Santiago | G62: =IFERROR(__xludf.DUMMYFUNCTION("""COMPUTED_VALUE"""),"Región Metropolitana") -> Región Metropolitana | H62: =IFERROR(__xludf.DUMMYFUNCTION("""COMPUTED_VALUE"""),1.836E7) -> 18360000
A63: =IFERROR(__xludf.DUMMYFUNCTION("""COMPUTED_VALUE"""),"CLI-0453") -> CLI-0453 | B63: =IFERROR(__xludf.DUMMYFUNCTION("""COMPUTED_VALUE"""),"20.046.968-0") -> 20.046.968-0 | C63: =IFERROR(__xludf.DUMMYFUNCTION("""COMPUTED_VALUE"""),"Fernanda Muñoz Díaz") -> Fernanda Muñoz Díaz | D63: =IFERROR(__xludf.DUMMYFUNCTION("""COMPUTED_VALUE"""),"fer.muñoz@outlook.cl") -> fer.muñoz@outlook.cl | E63: =IFERROR(__xludf.DUMMYFUNCTION("""COMPUTED_VALUE"""),"Santiago Centro") -> Santiago Centro | F63: =IFERROR(__xludf.DUMMYFUNCTION("""COMPUTED_VALUE"""),"Santiago") -> Santiago | G63: =IFERROR(__xludf.DUMMYFUNCTION("""COMPUTED_VALUE"""),"Región Metropolitana") -> Región Metropolitana | H63: =IFERROR(__xludf.DUMMYFUNCTION("""COMPUTED_VALUE"""),1.832E7) -> 18320000
A64: =IFERROR(__xludf.DUMMYFUNCTION("""COMPUTED_VALUE"""),"CLI-0270") -> CLI-0270 | B64: =IFERROR(__xludf.DUMMYFUNCTION("""COMPUTED_VALUE"""),"22.046.704-5") -> 22.046.704-5 | C64: =IFERROR(__xludf.DUMMYFUNCTION("""COMPUTED_VALUE"""),"Cristián González Sepúlveda") -> Cristián González Sepúlveda | D64: =IFERROR(__xludf.DUMMYFUNCTION("""COMPUTED_VALUE"""),"cri.gonzález@empresa.cl") -> cri.gonzález@empresa.cl | E64: =IFERROR(__xludf.DUMMYFUNCTION("""COMPUTED_VALUE"""),"Ñuñoa") -> Ñuñoa | F64: =IFERROR(__xludf.DUMMYFUNCTION("""COMPUTED_VALUE"""),"Santiago") -> Santiago | G64: =IFERROR(__xludf.DUMMYFUNCTION("""COMPUTED_VALUE"""),"Región Metropolitana") -> Región Metropolitana | H64: =IFERROR(__xludf.DUMMYFUNCTION("""COMPUTED_VALUE"""),1.828E7) -> 18280000
A65: =IFERROR(__xludf.DUMMYFUNCTION("""COMPUTED_VALUE"""),"CLI-0763") -> CLI-0763 | B65: =IFERROR(__xludf.DUMMYFUNCTION("""COMPUTED_VALUE"""),"19783717-4") -> 19783717-4 | C65: =IFERROR(__xludf.DUMMYFUNCTION("""COMPUTED_VALUE"""),"Javiera Soto Pérez") -> Javiera Soto Pérez | D65: =IFERROR(__xludf.DUMMYFUNCTION("""COMPUTED_VALUE"""),"jav.soto@empresa.cl") -> jav.soto@empresa.cl | E65: =IFERROR(__xludf.DUMMYFUNCTION("""COMPUTED_VALUE"""),"Providencia") -> Providencia | F65: =IFERROR(__xludf.DUMMYFUNCTION("""COMPUTED_VALUE"""),"Santiago") -> Santiago | G65: =IFERROR(__xludf.DUMMYFUNCTION("""COMPUTED_VALUE"""),"Región Metropolitana") -> Región Metropolitana | H65: =IFERROR(__xludf.DUMMYFUNCTION("""COMPUTED_VALUE"""),1.814E7) -> 18140000
A66: =IFERROR(__xludf.DUMMYFUNCTION("""COMPUTED_VALUE"""),"CLI-0530") -> CLI-0530 | B66: =IFERROR(__xludf.DUMMYFUNCTION("""COMPUTED_VALUE"""),"16.210.224-6") -> 16.210.224-6 | C66: =IFERROR(__xludf.DUMMYFUNCTION("""COMPUTED_VALUE"""),"Mauricio Morales González") -> Mauricio Morales González | D66: =IFERROR(__xludf.DUMMYFUNCTION("""COMPUTED_VALUE"""),"mau.morales@sura.cl") -> mau.morales@sura.cl | E66: =IFERROR(__xludf.DUMMYFUNCTION("""COMPUTED_VALUE"""),"Santiago Centro") -> Santiago Centro | F66: =IFERROR(__xludf.DUMMYFUNCTION("""COMPUTED_VALUE"""),"Santiago") -> Santiago | G66: =IFERROR(__xludf.DUMMYFUNCTION("""COMPUTED_VALUE"""),"Región Metropolitana") -> Región Metropolitana | H66: =IFERROR(__xludf.DUMMYFUNCTION("""COMPUTED_VALUE"""),1.802E7) -> 18020000
A67: =IFERROR(__xludf.DUMMYFUNCTION("""COMPUTED_VALUE"""),"CLI-0808") -> CLI-0808 | B67: =IFERROR(__xludf.DUMMYFUNCTION("""COMPUTED_VALUE"""),"17.574.755-4") -> 17.574.755-4 | C67: =IFERROR(__xludf.DUMMYFUNCTION("""COMPUTED_VALUE"""),"Esteban Díaz Rojas") -> Esteban Díaz Rojas | D67: =IFERROR(__xludf.DUMMYFUNCTION("""COMPUTED_VALUE"""),"est.díaz@servicios.cl") -> est.díaz@servicios.cl | E67: =IFERROR(__xludf.DUMMYFUNCTION("""COMPUTED_VALUE"""),"Ñuñoa") -> Ñuñoa | F67: =IFERROR(__xludf.DUMMYFUNCTION("""COMPUTED_VALUE"""),"Santiago") -> Santiago | G67: =IFERROR(__xludf.DUMMYFUNCTION("""COMPUTED_VALUE"""),"Región Metropolitana") -> Región Metropolitana | H67: =IFERROR(__xludf.DUMMYFUNCTION("""COMPUTED_VALUE"""),1.8E7) -> 18000000
A68: =IFERROR(__xludf.DUMMYFUNCTION("""COMPUTED_VALUE"""),"CLI-0045") -> CLI-0045 | B68: =IFERROR(__xludf.DUMMYFUNCTION("""COMPUTED_VALUE"""),"21720037-1") -> 21720037-1 | C68: =IFERROR(__xludf.DUMMYFUNCTION("""COMPUTED_VALUE"""),"Beatriz Tapia Valenzuela") -> Beatriz Tapia Valenzuela | D68: =IFERROR(__xludf.DUMMYFUNCTION("""COMPUTED_VALUE"""),"bea.tapia@servicios.cl") -> bea.tapia@servicios.cl | E68: =IFERROR(__xludf.DUMMYFUNCTION("""COMPUTED_VALUE"""),"Ñuñoa") -> Ñuñoa | F68: =IFERROR(__xludf.DUMMYFUNCTION("""COMPUTED_VALUE"""),"Santiago") -> Santiago | G68: =IFERROR(__xludf.DUMMYFUNCTION("""COMPUTED_VALUE"""),"Región Metropolitana") -> Región Metropolitana | H68: =IFERROR(__xludf.DUMMYFUNCTION("""COMPUTED_VALUE"""),1.799E7) -> 17990000
A69: =IFERROR(__xludf.DUMMYFUNCTION("""COMPUTED_VALUE"""),"CLI-0472") -> CLI-0472 | B69: =IFERROR(__xludf.DUMMYFUNCTION("""COMPUTED_VALUE"""),"12.218.638-K") -> 12.218.638-K | C69: =IFERROR(__xludf.DUMMYFUNCTION("""COMPUTED_VALUE"""),"Diego Rojas Vergara") -> Diego Rojas Vergara | D69: =IFERROR(__xludf.DUMMYFUNCTION("""COMPUTED_VALUE"""),"die.rojas@empresa.cl") -> die.rojas@empresa.cl | E69: =IFERROR(__xludf.DUMMYFUNCTION("""COMPUTED_VALUE"""),"Providencia") -> Providencia | F69: =IFERROR(__xludf.DUMMYFUNCTION("""COMPUTED_VALUE"""),"Santiago") -> Santiago | G69: =IFERROR(__xludf.DUMMYFUNCTION("""COMPUTED_VALUE"""),"Región Metropolitana") -> Región Metropolitana | H69: =IFERROR(__xludf.DUMMYFUNCTION("""COMPUTED_VALUE"""),1.799E7) -> 17990000
A70: =IFERROR(__xludf.DUMMYFUNCTION("""COMPUTED_VALUE"""),"CLI-0572") -> CLI-0572 | B70: =IFERROR(__xludf.DUMMYFUNCTION("""COMPUTED_VALUE"""),"20.122.214-9") -> 20.122.214-9 | C70: =IFERROR(__xludf.DUMMYFUNCTION("""COMPUTED_VALUE"""),"Tomas Silva Soto") -> Tomas Silva Soto | D70: =IFERROR(__xludf.DUMMYFUNCTION("""COMPUTED_VALUE"""),"tom.silva@outlook.cl") -> tom.silva@outlook.cl | E70: =IFERROR(__xludf.DUMMYFUNCTION("""COMPUTED_VALUE"""),"Santiago Centro") -> Santiago Centro | F70: =IFERROR(__xludf.DUMMYFUNCTION("""COMPUTED_VALUE"""),"Santiago") -> Santiago | G70: =IFERROR(__xludf.DUMMYFUNCTION("""COMPUTED_VALUE"""),"Región Metropolitana") -> Región Metropolitana | H70: =IFERROR(__xludf.DUMMYFUNCTION("""COMPUTED_VALUE"""),1.787E7) -> 17870000
A71: =IFERROR(__xludf.DUMMYFUNCTION("""COMPUTED_VALUE"""),"CLI-0600") -> CLI-0600 | B71: =IFERROR(__xludf.DUMMYFUNCTION("""COMPUTED_VALUE"""),"18.725.853-K") -> 18.725.853-K | C71: =IFERROR(__xludf.DUMMYFUNCTION("""COMPUTED_VALUE"""),"Claudio González Silva") -> Claudio González Silva | D71: =IFERROR(__xludf.DUMMYFUNCTION("""COMPUTED_VALUE"""),"cla.gonzález@sura.cl") -> cla.gonzález@sura.cl | E71: =IFERROR(__xludf.DUMMYFUNCTION("""COMPUTED_VALUE"""),"Las Condes") -> Las Condes | F71: =IFERROR(__xludf.DUMMYFUNCTION("""COMPUTED_VALUE"""),"Santiago") -> Santiago | G71: =IFERROR(__xludf.DUMMYFUNCTION("""COMPUTED_VALUE"""),"Región Metropolitana") -> Región Metropolitana | H71: =IFERROR(__xludf.DUMMYFUNCTION("""COMPUTED_VALUE"""),1.784E7) -> 17840000
A72: =IFERROR(__xludf.DUMMYFUNCTION("""COMPUTED_VALUE"""),"CLI-0655") -> CLI-0655 | B72: =IFERROR(__xludf.DUMMYFUNCTION("""COMPUTED_VALUE"""),"15.201.661-9") -> 15.201.661-9 | C72: =IFERROR(__xludf.DUMMYFUNCTION("""COMPUTED_VALUE"""),"Sofia Sepúlveda Muñoz") -> Sofia Sepúlveda Muñoz | D72: =IFERROR(__xludf.DUMMYFUNCTION("""COMPUTED_VALUE"""),"sof.sepúlveda@outlook.cl") -> sof.sepúlveda@outlook.cl | E72: =IFERROR(__xludf.DUMMYFUNCTION("""COMPUTED_VALUE"""),"Maipú") -> Maipú | F72: =IFERROR(__xludf.DUMMYFUNCTION("""COMPUTED_VALUE"""),"Santiago") -> Santiago | G72: =IFERROR(__xludf.DUMMYFUNCTION("""COMPUTED_VALUE"""),"Región Metropolitana") -> Región Metropolitana | H72: =IFERROR(__xludf.DUMMYFUNCTION("""COMPUTED_VALUE"""),1.78E7) -> 17800000
A73: =IFERROR(__xludf.DUMMYFUNCTION("""COMPUTED_VALUE"""),"CLI-0315") -> CLI-0315 | B73: =IFERROR(__xludf.DUMMYFUNCTION("""COMPUTED_VALUE"""),"16.228.639-5") -> 16.228.639-5 | C73: =IFERROR(__xludf.DUMMYFUNCTION("""COMPUTED_VALUE"""),"Macarena Muñoz Araya") -> Macarena Muñoz Araya | D73: =IFERROR(__xludf.DUMMYFUNCTION("""COMPUTED_VALUE"""),"mac.muñoz@consultora.cl") -> mac.muñoz@consultora.cl | E73: =IFERROR(__xludf.DUMMYFUNCTION("""COMPUTED_VALUE"""),"Santiago Centro") -> Santiago Centro | F73: =IFERROR(__xludf.DUMMYFUNCTION("""COMPUTED_VALUE"""),"Santiago") -> Santiago | G73: =IFERROR(__xludf.DUMMYFUNCTION("""COMPUTED_VALUE"""),"Región Metropolitana") -> Región Metropolitana | H73: =IFERROR(__xludf.DUMMYFUNCTION("""COMPUTED_VALUE"""),1.768E7) -> 17680000
A74: =IFERROR(__xludf.DUMMYFUNCTION("""COMPUTED_VALUE"""),"CLI-0389") -> CLI-0389 | B74: =IFERROR(__xludf.DUMMYFUNCTION("""COMPUTED_VALUE"""),"17.114.870-6") -> 17.114.870-6 | C74: =IFERROR(__xludf.DUMMYFUNCTION("""COMPUTED_VALUE"""),"Javiera Espinoza Contreras") -> Javiera Espinoza Contreras | D74: =IFERROR(__xludf.DUMMYFUNCTION("""COMPUTED_VALUE"""),"jav.espinoza@empresa.cl") -> jav.espinoza@empresa.cl | E74: =IFERROR(__xludf.DUMMYFUNCTION("""COMPUTED_VALUE"""),"Maipú") -> Maipú | F74: =IFERROR(__xludf.DUMMYFUNCTION("""COMPUTED_VALUE"""),"Santiago") -> Santiago | G74: =IFERROR(__xludf.DUMMYFUNCTION("""COMPUTED_VALUE"""),"Región Metropolitana") -> Región Metropolitana | H74: =IFERROR(__xludf.DUMMYFUNCTION("""COMPUTED_VALUE"""),1.759E7) -> 17590000
A75: =IFERROR(__xludf.DUMMYFUNCTION("""COMPUTED_VALUE"""),"CLI-0549") -> CLI-0549 | B75: =IFERROR(__xludf.DUMMYFUNCTION("""COMPUTED_VALUE"""),"16714058-4") -> 16714058-4 | C75: =IFERROR(__xludf.DUMMYFUNCTION("""COMPUTED_VALUE"""),"Macarena Sepúlveda Vergara") -> Macarena Sepúlveda Vergara | D75: =IFERROR(__xludf.DUMMYFUNCTION("""COMPUTED_VALUE"""),"mac.sepúlveda@gmail.com") -> mac.sepúlveda@gmail.com | E75: =IFERROR(__xludf.DUMMYFUNCTION("""COMPUTED_VALUE"""),"Las Condes") -> Las Condes | F75: =IFERROR(__xludf.DUMMYFUNCTION("""COMPUTED_VALUE"""),"Santiago") -> Santiago | G75: =IFERROR(__xludf.DUMMYFUNCTION("""COMPUTED_VALUE"""),"Región Metropolitana") -> Región Metropolitana | H75: =IFERROR(__xludf.DUMMYFUNCTION("""COMPUTED_VALUE"""),1.754E7) -> 17540000
A76: =IFERROR(__xludf.DUMMYFUNCTION("""COMPUTED_VALUE"""),"CLI-0247") -> CLI-0247 | B76: =IFERROR(__xludf.DUMMYFUNCTION("""COMPUTED_VALUE"""),"20.227.751-1") -> 20.227.751-1 | C76: =IFERROR(__xludf.DUMMYFUNCTION("""COMPUTED_VALUE"""),"Valentina González Tapia") -> Valentina González Tapia | D76: =IFERROR(__xludf.DUMMYFUNCTION("""COMPUTED_VALUE"""),"val.gonzález@servicios.cl") -> val.gonzález@servicios.cl | E76: =IFERROR(__xludf.DUMMYFUNCTION("""COMPUTED_VALUE"""),"Santiago Centro") -> Santiago Centro | F76: =IFERROR(__xludf.DUMMYFUNCTION("""COMPUTED_VALUE"""),"Santiago") -> Santiago | G76: =IFERROR(__xludf.DUMMYFUNCTION("""COMPUTED_VALUE"""),"Región Metropolitana") -> Región Metropolitana | H76: =IFERROR(__xludf.DUMMYFUNCTION("""COMPUTED_VALUE"""),1.753E7) -> 17530000
A77: =IFERROR(__xludf.DUMMYFUNCTION("""COMPUTED_VALUE"""),"CLI-0684") -> CLI-0684 | B77: =IFERROR(__xludf.DUMMYFUNCTION("""COMPUTED_VALUE"""),"15.205.400-3") -> 15.205.400-3 | C77: =IFERROR(__xludf.DUMMYFUNCTION("""COMPUTED_VALUE"""),"Diego Espinoza Vergara") -> Diego Espinoza Vergara | D77: =IFERROR(__xludf.DUMMYFUNCTION("""COMPUTED_VALUE"""),"die.espinoza@sura.cl") -> die.espinoza@sura.cl | E77: =IFERROR(__xludf.DUMMYFUNCTION("""COMPUTED_VALUE"""),"Providencia") -> Providencia | F77: =IFERROR(__xludf.DUMMYFUNCTION("""COMPUTED_VALUE"""),"Santiago") -> Santiago | G77: =IFERROR(__xludf.DUMMYFUNCTION("""COMPUTED_VALUE"""),"Región Metropolitana") -> Región Metropolitana | H77: =IFERROR(__xludf.DUMMYFUNCTION("""COMPUTED_VALUE"""),1.752E7) -> 17520000
A78: =IFERROR(__xludf.DUMMYFUNCTION("""COMPUTED_VALUE"""),"CLI-0846") -> CLI-0846 | B78: =IFERROR(__xludf.DUMMYFUNCTION("""COMPUTED_VALUE"""),"20.607.532-5") -> 20.607.532-5 | C78: =IFERROR(__xludf.DUMMYFUNCTION("""COMPUTED_VALUE"""),"Diego Soto Muñoz") -> Diego Soto Muñoz | D78: =IFERROR(__xludf.DUMMYFUNCTION("""COMPUTED_VALUE"""),"die.soto@sura.cl") -> die.soto@sura.cl | E78: =IFERROR(__xludf.DUMMYFUNCTION("""COMPUTED_VALUE"""),"Las Condes") -> Las Condes | F78: =IFERROR(__xludf.DUMMYFUNCTION("""COMPUTED_VALUE"""),"Santiago") -> Santiago | G78: =IFERROR(__xludf.DUMMYFUNCTION("""COMPUTED_VALUE"""),"Región Metropolitana") -> Región Metropolitana | H78: =IFERROR(__xludf.DUMMYFUNCTION("""COMPUTED_VALUE"""),1.751E7) -> 17510000
A79: =IFERROR(__xludf.DUMMYFUNCTION("""COMPUTED_VALUE"""),"CLI-0414") -> CLI-0414 | B79: =IFERROR(__xludf.DUMMYFUNCTION("""COMPUTED_VALUE"""),"22376288-1") -> 22376288-1 | C79: =IFERROR(__xludf.DUMMYFUNCTION("""COMPUTED_VALUE"""),"Tomas Vergara Araya") -> Tomas Vergara Araya | D79: =IFERROR(__xludf.DUMMYFUNCTION("""COMPUTED_VALUE"""),"tom.vergara@sura.cl") -> tom.vergara@sura.cl | E79: =IFERROR(__xludf.DUMMYFUNCTION("""COMPUTED_VALUE"""),"Maipú") -> Maipú | F79: =IFERROR(__xludf.DUMMYFUNCTION("""COMPUTED_VALUE"""),"Santiago") -> Santiago | G79: =IFERROR(__xludf.DUMMYFUNCTION("""COMPUTED_VALUE"""),"Región Metropolitana") -> Región Metropolitana | H79: =IFERROR(__xludf.DUMMYFUNCTION("""COMPUTED_VALUE"""),1.75E7) -> 17500000
A80: =IFERROR(__xludf.DUMMYFUNCTION("""COMPUTED_VALUE"""),"CLI-0301") -> CLI-0301 | B80: =IFERROR(__xludf.DUMMYFUNCTION("""COMPUTED_VALUE"""),"13.137.745-7") -> 13.137.745-7 | C80: =IFERROR(__xludf.DUMMYFUNCTION("""COMPUTED_VALUE"""),"Javiera Soto Soto") -> Javiera Soto Soto | D80: =IFERROR(__xludf.DUMMYFUNCTION("""COMPUTED_VALUE"""),"jav.soto@gmail.com") -> jav.soto@gmail.com | E80: =IFERROR(__xludf.DUMMYFUNCTION("""COMPUTED_VALUE"""),"Ñuñoa") -> Ñuñoa | F80: =IFERROR(__xludf.DUMMYFUNCTION("""COMPUTED_VALUE"""),"Santiago") -> Santiago | G80: =IFERROR(__xludf.DUMMYFUNCTION("""COMPUTED_VALUE"""),"Región Metropolitana") -> Región Metropolitana | H80: =IFERROR(__xludf.DUMMYFUNCTION("""COMPUTED_VALUE"""),1.744E7) -> 17440000
A81: =IFERROR(__xludf.DUMMYFUNCTION("""COMPUTED_VALUE"""),"CLI-0802") -> CLI-0802 | B81: =IFERROR(__xludf.DUMMYFUNCTION("""COMPUTED_VALUE"""),"22.452.644-K") -> 22.452.644-K | C81: =IFERROR(__xludf.DUMMYFUNCTION("""COMPUTED_VALUE"""),"Claudio González Pérez") -> Claudio González Pérez | D81: =IFERROR(__xludf.DUMMYFUNCTION("""COMPUTED_VALUE"""),"cla.gonzález@gmail.com") -> cla.gonzález@gmail.com | E81: =IFERROR(__xludf.DUMMYFUNCTION("""COMPUTED_VALUE"""),"Las Condes") -> Las Condes | F81: =IFERROR(__xludf.DUMMYFUNCTION("""COMPUTED_VALUE"""),"Santiago") -> Santiago | G81: =IFERROR(__xludf.DUMMYFUNCTION("""COMPUTED_VALUE"""),"Región Metropolitana") -> Región Metropolitana | H81: =IFERROR(__xludf.DUMMYFUNCTION("""COMPUTED_VALUE"""),1.738E7) -> 17380000
A82: =IFERROR(__xludf.DUMMYFUNCTION("""COMPUTED_VALUE"""),"CLI-0348") -> CLI-0348 | B82: =IFERROR(__xludf.DUMMYFUNCTION("""COMPUTED_VALUE"""),"18.968.758-6") -> 18.968.758-6 | C82: =IFERROR(__xludf.DUMMYFUNCTION("""COMPUTED_VALUE"""),"Felipe Araya Fuentes") -> Felipe Araya Fuentes | D82: =IFERROR(__xludf.DUMMYFUNCTION("""COMPUTED_VALUE"""),"fel.araya@consultora.cl") -> fel.araya@consultora.cl | E82: =IFERROR(__xludf.DUMMYFUNCTION("""COMPUTED_VALUE"""),"Santiago Centro") -> Santiago Centro | F82: =IFERROR(__xludf.DUMMYFUNCTION("""COMPUTED_VALUE"""),"Santiago") -> Santiago | G82: =IFERROR(__xludf.DUMMYFUNCTION("""COMPUTED_VALUE"""),"Región Metropolitana") -> Región Metropolitana | H82: =IFERROR(__xludf.DUMMYFUNCTION("""COMPUTED_VALUE"""),1.735E7) -> 17350000
A83: =IFERROR(__xludf.DUMMYFUNCTION("""COMPUTED_VALUE"""),"CLI-0556") -> CLI-0556 | B83: =IFERROR(__xludf.DUMMYFUNCTION("""COMPUTED_VALUE"""),"19427433-5") -> 19427433-5 | C83: =IFERROR(__xludf.DUMMYFUNCTION("""COMPUTED_VALUE"""),"Gonzalo Vergara Rojas") -> Gonzalo Vergara Rojas | D83: =IFERROR(__xludf.DUMMYFUNCTION("""COMPUTED_VALUE"""),"gon.vergara@consultora.cl") -> gon.vergara@consultora.cl | E83: =IFERROR(__xludf.DUMMYFUNCTION("""COMPUTED_VALUE"""),"Providencia") -> Providencia | F83: =IFERROR(__xludf.DUMMYFUNCTION("""COMPUTED_VALUE"""),"Santiago") -> Santiago | G83: =IFERROR(__xludf.DUMMYFUNCTION("""COMPUTED_VALUE"""),"Región Metropolitana") -> Región Metropolitana | H83: =IFERROR(__xludf.DUMMYFUNCTION("""COMPUTED_VALUE"""),1.732E7) -> 17320000
A84: =IFERROR(__xludf.DUMMYFUNCTION("""COMPUTED_VALUE"""),"CLI-0815") -> CLI-0815 | B84: =IFERROR(__xludf.DUMMYFUNCTION("""COMPUTED_VALUE"""),"20481651-5") -> 20481651-5 | C84: =IFERROR(__xludf.DUMMYFUNCTION("""COMPUTED_VALUE"""),"Javiera Silva Contreras") -> Javiera Silva Contreras | D84: =IFERROR(__xludf.DUMMYFUNCTION("""COMPUTED_VALUE"""),"jav.silva@sura.cl") -> jav.silva@sura.cl | E84: =IFERROR(__xludf.DUMMYFUNCTION("""COMPUTED_VALUE"""),"Maipú") -> Maipú | F84: =IFERROR(__xludf.DUMMYFUNCTION("""COMPUTED_VALUE"""),"Santiago") -> Santiago | G84: =IFERROR(__xludf.DUMMYFUNCTION("""COMPUTED_VALUE"""),"Región Metropolitana") -> Región Metropolitana | H84: =IFERROR(__xludf.DUMMYFUNCTION("""COMPUTED_VALUE"""),1.718E7) -> 17180000
A85: =IFERROR(__xludf.DUMMYFUNCTION("""COMPUTED_VALUE"""),"CLI-0474") -> CLI-0474 | B85: =IFERROR(__xludf.DUMMYFUNCTION("""COMPUTED_VALUE"""),"16989738-2") -> 16989738-2 | C85: =IFERROR(__xludf.DUMMYFUNCTION("""COMPUTED_VALUE"""),"Claudio Valenzuela López") -> Claudio Valenzuela López | D85: =IFERROR(__xludf.DUMMYFUNCTION("""COMPUTED_VALUE"""),"cla.valenzuela@sura.cl") -> cla.valenzuela@sura.cl | E85: =IFERROR(__xludf.DUMMYFUNCTION("""COMPUTED_VALUE"""),"Maipú") -> Maipú | F85: =IFERROR(__xludf.DUMMYFUNCTION("""COMPUTED_VALUE"""),"Santiago") -> Santiago | G85: =IFERROR(__xludf.DUMMYFUNCTION("""COMPUTED_VALUE"""),"Región Metropolitana") -> Región Metropolitana | H85: =IFERROR(__xludf.DUMMYFUNCTION("""COMPUTED_VALUE"""),1.706E7) -> 17060000
A86: =IFERROR(__xludf.DUMMYFUNCTION("""COMPUTED_VALUE"""),"CLI-0761") -> CLI-0761 | B86: =IFERROR(__xludf.DUMMYFUNCTION("""COMPUTED_VALUE"""),"17191972-2") -> 17191972-2 | C86: =IFERROR(__xludf.DUMMYFUNCTION("""COMPUTED_VALUE"""),"Andrea Sepúlveda López") -> Andrea Sepúlveda López | D86: =IFERROR(__xludf.DUMMYFUNCTION("""COMPUTED_VALUE"""),"and.sepúlveda@consultora.cl") -> and.sepúlveda@consultora.cl | E86: =IFERROR(__xludf.DUMMYFUNCTION("""COMPUTED_VALUE"""),"Las Condes") -> Las Condes | F86: =IFERROR(__xludf.DUMMYFUNCTION("""COMPUTED_VALUE"""),"Santiago") -> Santiago | G86: =IFERROR(__xludf.DUMMYFUNCTION("""COMPUTED_VALUE"""),"Región Metropolitana") -> Región Metropolitana | H86: =IFERROR(__xludf.DUMMYFUNCTION("""COMPUTED_VALUE"""),1.704E7) -> 17040000
A87: =IFERROR(__xludf.DUMMYFUNCTION("""COMPUTED_VALUE"""),"CLI-0603") -> CLI-0603 | B87: =IFERROR(__xludf.DUMMYFUNCTION("""COMPUTED_VALUE"""),"15.504.619-7") -> 15.504.619-7 | C87: =IFERROR(__xludf.DUMMYFUNCTION("""COMPUTED_VALUE"""),"Francisca Araya Sepúlveda") -> Francisca Araya Sepúlveda | D87: =IFERROR(__xludf.DUMMYFUNCTION("""COMPUTED_VALUE"""),"fra.araya@empresa.cl") -> fra.araya@empresa.cl | E87: =IFERROR(__xludf.DUMMYFUNCTION("""COMPUTED_VALUE"""),"Ñuñoa") -> Ñuñoa | F87: =IFERROR(__xludf.DUMMYFUNCTION("""COMPUTED_VALUE"""),"Santiago") -> Santiago | G87: =IFERROR(__xludf.DUMMYFUNCTION("""COMPUTED_VALUE"""),"Región Metropolitana") -> Región Metropolitana | H87: =IFERROR(__xludf.DUMMYFUNCTION("""COMPUTED_VALUE"""),1.694E7) -> 16940000
A88: =IFERROR(__xludf.DUMMYFUNCTION("""COMPUTED_VALUE"""),"CLI-0545") -> CLI-0545 | B88: =IFERROR(__xludf.DUMMYFUNCTION("""COMPUTED_VALUE"""),"11.855.680-0") -> 11.855.680-0 | C88: =IFERROR(__xludf.DUMMYFUNCTION("""COMPUTED_VALUE"""),"Francisca Silva Rodríguez") -> Francisca Silva Rodríguez | D88: =IFERROR(__xludf.DUMMYFUNCTION("""COMPUTED_VALUE"""),"fra.silva@consultora.cl") -> fra.silva@consultora.cl | E88: =IFERROR(__xludf.DUMMYFUNCTION("""COMPUTED_VALUE"""),"Las Condes") -> Las Condes | F88: =IFERROR(__xludf.DUMMYFUNCTION("""COMPUTED_VALUE"""),"Santiago") -> Santiago | G88: =IFERROR(__xludf.DUMMYFUNCTION("""COMPUTED_VALUE"""),"Región Metropolitana") -> Región Metropolitana | H88: =IFERROR(__xludf.DUMMYFUNCTION("""COMPUTED_VALUE"""),1.686E7) -> 16860000
A89: =IFERROR(__xludf.DUMMYFUNCTION("""COMPUTED_VALUE"""),"CLI-0909") -> CLI-0909 | B89: =IFERROR(__xludf.DUMMYFUNCTION("""COMPUTED_VALUE"""),"15.114.550-4") -> 15.114.550-4 | C89: =IFERROR(__xludf.DUMMYFUNCTION("""COMPUTED_VALUE"""),"Andrea Díaz Araya") -> Andrea Díaz Araya | D89: =IFERROR(__xludf.DUMMYFUNCTION("""COMPUTED_VALUE"""),"and.díaz@empresa.cl") -> and.díaz@empresa.cl | E89: =IFERROR(__xludf.DUMMYFUNCTION("""COMPUTED_VALUE"""),"Santiago Centro") -> Santiago Centro | F89: =IFERROR(__xludf.DUMMYFUNCTION("""COMPUTED_VALUE"""),"Santiago") -> Santiago | G89: =IFERROR(__xludf.DUMMYFUNCTION("""COMPUTED_VALUE"""),"Región Metropolitana") -> Región Metropolitana | H89: =IFERROR(__xludf.DUMMYFUNCTION("""COMPUTED_VALUE"""),1.68E7) -> 16800000
A90: =IFERROR(__xludf.DUMMYFUNCTION("""COMPUTED_VALUE"""),"CLI-0701") -> CLI-0701 | B90: =IFERROR(__xludf.DUMMYFUNCTION("""COMPUTED_VALUE"""),"15196514-5") -> 15196514-5 | C90: =IFERROR(__xludf.DUMMYFUNCTION("""COMPUTED_VALUE"""),"Constanza López Díaz") -> Constanza López Díaz | D90: =IFERROR(__xludf.DUMMYFUNCTION("""COMPUTED_VALUE"""),"con.lópez@servicios.cl") -> con.lópez@servicios.cl | E90: =IFERROR(__xludf.DUMMYFUNCTION("""COMPUTED_VALUE"""),"Las Condes") -> Las Condes | F90: =IFERROR(__xludf.DUMMYFUNCTION("""COMPUTED_VALUE"""),"Santiago") -> Santiago | G90: =IFERROR(__xludf.DUMMYFUNCTION("""COMPUTED_VALUE"""),"Región Metropolitana") -> Región Metropolitana | H90: =IFERROR(__xludf.DUMMYFUNCTION("""COMPUTED_VALUE"""),1.663E7) -> 16630000
A91: =IFERROR(__xludf.DUMMYFUNCTION("""COMPUTED_VALUE"""),"CLI-0359") -> CLI-0359 | B91: =IFERROR(__xludf.DUMMYFUNCTION("""COMPUTED_VALUE"""),"17.428.855-K") -> 17.428.855-K | C91: =IFERROR(__xludf.DUMMYFUNCTION("""COMPUTED_VALUE"""),"Paula Vergara Silva") -> Paula Vergara Silva | D91: =IFERROR(__xludf.DUMMYFUNCTION("""COMPUTED_VALUE"""),"pau.vergara@consultora.cl") -> pau.vergara@consultora.cl | E91: =IFERROR(__xludf.DUMMYFUNCTION("""COMPUTED_VALUE"""),"Providencia") -> Providencia | F91: =IFERROR(__xludf.DUMMYFUNCTION("""COMPUTED_VALUE"""),"Santiago") -> Santiago | G91: =IFERROR(__xludf.DUMMYFUNCTION("""COMPUTED_VALUE"""),"Región Metropolitana") -> Región Metropolitana | H91: =IFERROR(__xludf.DUMMYFUNCTION("""COMPUTED_VALUE"""),1.656E7) -> 16560000
A92: =IFERROR(__xludf.DUMMYFUNCTION("""COMPUTED_VALUE"""),"CLI-0510") -> CLI-0510 | B92: =IFERROR(__xludf.DUMMYFUNCTION("""COMPUTED_VALUE"""),"13.365.982-4") -> 13.365.982-4 | C92: =IFERROR(__xludf.DUMMYFUNCTION("""COMPUTED_VALUE"""),"Esteban Contreras Morales") -> Esteban Contreras Morales | D92: =IFERROR(__xludf.DUMMYFUNCTION("""COMPUTED_VALUE"""),"est.contreras@servicios.cl") -> est.contreras@servicios.cl | E92: =IFERROR(__xludf.DUMMYFUNCTION("""COMPUTED_VALUE"""),"Las Condes") -> Las Condes | F92: =IFERROR(__xludf.DUMMYFUNCTION("""COMPUTED_VALUE"""),"Santiago") -> Santiago | G92: =IFERROR(__xludf.DUMMYFUNCTION("""COMPUTED_VALUE"""),"Región Metropolitana") -> Región Metropolitana | H92: =IFERROR(__xludf.DUMMYFUNCTION("""COMPUTED_VALUE"""),1.654E7) -> 16540000
A93: =IFERROR(__xludf.DUMMYFUNCTION("""COMPUTED_VALUE"""),"CLI-0833") -> CLI-0833 | B93: =IFERROR(__xludf.DUMMYFUNCTION("""COMPUTED_VALUE"""),"13.089.278-7") -> 13.089.278-7 | C93: =IFERROR(__xludf.DUMMYFUNCTION("""COMPUTED_VALUE"""),"Daniela Tapia Tapia") -> Daniela Tapia Tapia | D93: =IFERROR(__xludf.DUMMYFUNCTION("""COMPUTED_VALUE"""),"dan.tapia@servicios.cl") -> dan.tapia@servicios.cl | E93: =IFERROR(__xludf.DUMMYFUNCTION("""COMPUTED_VALUE"""),"Providencia") -> Providencia | F93: =IFERROR(__xludf.DUMMYFUNCTION("""COMPUTED_VALUE"""),"Santiago") -> Santiago | G93: =IFERROR(__xludf.DUMMYFUNCTION("""COMPUTED_VALUE"""),"Región Metropolitana") -> Región Metropolitana | H93: =IFERROR(__xludf.DUMMYFUNCTION("""COMPUTED_VALUE"""),1.652E7) -> 16520000
A94: =IFERROR(__xludf.DUMMYFUNCTION("""COMPUTED_VALUE"""),"CLI-0598") -> CLI-0598 | B94: =IFERROR(__xludf.DUMMYFUNCTION("""COMPUTED_VALUE"""),"22.427.853-5") -> 22.427.853-5 | C94: =IFERROR(__xludf.DUMMYFUNCTION("""COMPUTED_VALUE"""),"Mauricio Tapia Pérez") -> Mauricio Tapia Pérez | D94: =IFERROR(__xludf.DUMMYFUNCTION("""COMPUTED_VALUE"""),"mau.tapia@outlook.cl") -> mau.tapia@outlook.cl | E94: =IFERROR(__xludf.DUMMYFUNCTION("""COMPUTED_VALUE"""),"Providencia") -> Providencia | F94: =IFERROR(__xludf.DUMMYFUNCTION("""COMPUTED_VALUE"""),"Santiago") -> Santiago | G94: =IFERROR(__xludf.DUMMYFUNCTION("""COMPUTED_VALUE"""),"Región Metropolitana") -> Región Metropolitana | H94: =IFERROR(__xludf.DUMMYFUNCTION("""COMPUTED_VALUE"""),1.647E7) -> 16470000
A95: =IFERROR(__xludf.DUMMYFUNCTION("""COMPUTED_VALUE"""),"CLI-0268") -> CLI-0268 | B95: =IFERROR(__xludf.DUMMYFUNCTION("""COMPUTED_VALUE"""),"13.273.886-0") -> 13.273.886-0 | C95: =IFERROR(__xludf.DUMMYFUNCTION("""COMPUTED_VALUE"""),"Javier Tapia Contreras") -> Javier Tapia Contreras | D95: =IFERROR(__xludf.DUMMYFUNCTION("""COMPUTED_VALUE"""),"jav.tapia@sura.cl") -> jav.tapia@sura.cl | E95: =IFERROR(__xludf.DUMMYFUNCTION("""COMPUTED_VALUE"""),"Santiago Centro") -> Santiago Centro | F95: =IFERROR(__xludf.DUMMYFUNCTION("""COMPUTED_VALUE"""),"Santiago") -> Santiago | G95: =IFERROR(__xludf.DUMMYFUNCTION("""COMPUTED_VALUE"""),"Región Metropolitana") -> Región Metropolitana | H95: =IFERROR(__xludf.DUMMYFUNCTION("""COMPUTED_VALUE"""),1.645E7) -> 16450000
A96: =IFERROR(__xludf.DUMMYFUNCTION("""COMPUTED_VALUE"""),"CLI-0632") -> CLI-0632 | B96: =IFERROR(__xludf.DUMMYFUNCTION("""COMPUTED_VALUE"""),"20.604.176-8") -> 20.604.176-8 | C96: =IFERROR(__xludf.DUMMYFUNCTION("""COMPUTED_VALUE"""),"Mauricio Muñoz Espinoza") -> Mauricio Muñoz Espinoza | D96: =IFERROR(__xludf.DUMMYFUNCTION("""COMPUTED_VALUE"""),"mau.muñoz@consultora.cl") -> mau.muñoz@consultora.cl | E96: =IFERROR(__xludf.DUMMYFUNCTION("""COMPUTED_VALUE"""),"Maipú") -> Maipú | F96: =IFERROR(__xludf.DUMMYFUNCTION("""COMPUTED_VALUE"""),"Santiago") -> Santiago | G96: =IFERROR(__xludf.DUMMYFUNCTION("""COMPUTED_VALUE"""),"Región Metropolitana") -> Región Metropolitana | H96: =IFERROR(__xludf.DUMMYFUNCTION("""COMPUTED_VALUE"""),1.642E7) -> 16420000
A97: =IFERROR(__xludf.DUMMYFUNCTION("""COMPUTED_VALUE"""),"CLI-0398") -> CLI-0398 | B97: =IFERROR(__xludf.DUMMYFUNCTION("""COMPUTED_VALUE"""),"14084888-K") -> 14084888-K | C97: =IFERROR(__xludf.DUMMYFUNCTION("""COMPUTED_VALUE"""),"Diego Contreras Araya") -> Diego Contreras Araya | D97: =IFERROR(__xludf.DUMMYFUNCTION("""COMPUTED_VALUE"""),"die.contreras@sura.cl") -> die.contreras@sura.cl | E97: =IFERROR(__xludf.DUMMYFUNCTION("""COMPUTED_VALUE"""),"Las Condes") -> Las Condes | F97: =IFERROR(__xludf.DUMMYFUNCTION("""COMPUTED_VALUE"""),"Santiago") -> Santiago | G97: =IFERROR(__xludf.DUMMYFUNCTION("""COMPUTED_VALUE"""),"Región Metropolitana") -> Región Metropolitana | H97: =IFERROR(__xludf.DUMMYFUNCTION("""COMPUTED_VALUE"""),1.636E7) -> 16360000
A98: =IFERROR(__xludf.DUMMYFUNCTION("""COMPUTED_VALUE"""),"CLI-0110") -> CLI-0110 | B98: =IFERROR(__xludf.DUMMYFUNCTION("""COMPUTED_VALUE"""),"13.520.150-2") -> 13.520.150-2 | C98: =IFERROR(__xludf.DUMMYFUNCTION("""COMPUTED_VALUE"""),"Sebastián Pérez Soto") -> Sebastián Pérez Soto | D98: =IFERROR(__xludf.DUMMYFUNCTION("""COMPUTED_VALUE"""),"seb.pérez@sura.cl") -> seb.pérez@sura.cl | E98: =IFERROR(__xludf.DUMMYFUNCTION("""COMPUTED_VALUE"""),"Las Condes") -> Las Condes | F98: =IFERROR(__xludf.DUMMYFUNCTION("""COMPUTED_VALUE"""),"Santiago") -> Santiago | G98: =IFERROR(__xludf.DUMMYFUNCTION("""COMPUTED_VALUE"""),"Región Metropolitana") -> Región Metropolitana | H98: =IFERROR(__xludf.DUMMYFUNCTION("""COMPUTED_VALUE"""),1.633E7) -> 16330000
A99: =IFERROR(__xludf.DUMMYFUNCTION("""COMPUTED_VALUE"""),"CLI-0230") -> CLI-0230 | B99: =IFERROR(__xludf.DUMMYFUNCTION("""COMPUTED_VALUE"""),"16.752.592-9") -> 16.752.592-9 | C99: =IFERROR(__xludf.DUMMYFUNCTION("""COMPUTED_VALUE"""),"Álvaro Soto Vergara") -> Álvaro Soto Vergara | D99: =IFERROR(__xludf.DUMMYFUNCTION("""COMPUTED_VALUE"""),"álv.soto@gmail.com") -> álv.soto@gmail.com | E99: =IFERROR(__xludf.DUMMYFUNCTION("""COMPUTED_VALUE"""),"Santiago Centro") -> Santiago Centro | F99: =IFERROR(__xludf.DUMMYFUNCTION("""COMPUTED_VALUE"""),"Santiago") -> Santiago | G99: =IFERROR(__xludf.DUMMYFUNCTION("""COMPUTED_VALUE"""),"Región Metropolitana") -> Región Metropolitana | H99: =IFERROR(__xludf.DUMMYFUNCTION("""COMPUTED_VALUE"""),1.63E7) -> 16300000
A100: =IFERROR(__xludf.DUMMYFUNCTION("""COMPUTED_VALUE"""),"CLI-0729") -> CLI-0729 | B100: =IFERROR(__xludf.DUMMYFUNCTION("""COMPUTED_VALUE"""),"19.479.808-K") -> 19.479.808-K | C100: =IFERROR(__xludf.DUMMYFUNCTION("""COMPUTED_VALUE"""),"Javiera Silva Araya") -> Javiera Silva Araya | D100: =IFERROR(__xludf.DUMMYFUNCTION("""COMPUTED_VALUE"""),"jav.silva@gmail.com") -> jav.silva@gmail.com | E100: =IFERROR(__xludf.DUMMYFUNCTION("""COMPUTED_VALUE"""),"Ñuñoa") -> Ñuñoa | F100: =IFERROR(__xludf.DUMMYFUNCTION("""COMPUTED_VALUE"""),"Santiago") -> Santiago | G100: =IFERROR(__xludf.DUMMYFUNCTION("""COMPUTED_VALUE"""),"Región Metropolitana") -> Región Metropolitana | H100: =IFERROR(__xludf.DUMMYFUNCTION("""COMPUTED_VALUE"""),1.629E7) -> 16290000
...

Sheet Bitácora Higiene
A1: 4 funciones aplicadas, las columnas afectadas y el porcentaje de errores corregidos.
A2: Funciones: | B2: Columnas Afectadas:
A3: NOMPROPIO | B3: Nombre_Completo
A4: ESPACIOS | B4: RUT_Cliente
A5: TEXTJOIN | B5: Comuna Ciudad Region
A8: Se filtran 44 duplicados y se pasan valores en CLP al formato con punto
